{
  "_updated": "2026-07-05T01:30:31.143Z",
  "BTCUSDT": {
    "15M": {
      "symbol": "BTCUSDT",
      "timeframe": "15M",
      "open": 62994.01,
      "high": 62994.01,
      "low": 62838,
      "close": 62940.04,
      "volume": 70.6257,
      "wickRange": 156.01,
      "vwap": 63007.9904,
      "ema50": 63027.1939,
      "ema100": null,
      "ema200": 62370.4451,
      "sma50": null,
      "sma200": null,
      "rsi": 40.6321,
      "stochK": 3.5636,
      "stochD": 9.6614,
      "macdLine": -30.0729,
      "macdHist": -39.5403,
      "atr": 132.3527,
      "volSMA20": 101.3953,
      "bbWidth": 0.8391,
      "trendBias": -0.5,
      "mfi": 7.58,
      "fracResistance": 63241.33,
      "fracSupport": 62927.98,
      "fracResActive": 1,
      "fracSupActive": 1,
      "fvgBullActive": 0,
      "fvgBullLo": 63098,
      "fvgBullHi": 63144,
      "fvgBearActive": 0,
      "fvgBearLo": 63060,
      "fvgBearHi": 63144,
      "coffinFormed": 1,
      "coffinHi": 62994.01,
      "coffinLo": 62940.04,
      "coffinArmed": 1,
      "coffinBreakLong": 0,
      "coffinBreakShort": 0,
      "coffinAtLevel": 1,
      "ewCount": 0,
      "ewDirection": 1,
      "ewWaveType": "UNKNOWN",
      "ewCorrPattern": "NONE",
      "ewInvalidated": 0,
      "ewBWave": 0,
      "ewDivergence": 0,
      "ewAlternation": "NONE",
      "ewFibTarget": null,
      "ewFibRetrace": null,
      "ewPriorW4High": null,
      "ewPriorW4Low": null,
      "dailyHigh": null,
      "dailyLow": null,
      "dailyOpenHour": null,
      "dailyOpenSession": null,
      "emaStackAligned": 0,
      "volRegime": "NEUTRAL",
      "choch": 0,
      "chochLevel": null,
      "rsiDivBearish": 0,
      "rsiDivBullish": 0,
      "macdDivBearish": 0,
      "macdDivBullish": 0,
      "bosVolConfirmed": 0,
      "bosVolRatio": null,
      "candleType": null,
      "consolidationForming": 0,
      "consolidationBars": 0,
      "obActive": 0,
      "obType": null,
      "obHigh": null,
      "obLow": null,
      "marketState": null,
      "bdkb": {
        "score": -42,
        "longScore": 0,
        "shortScore": 42,
        "state": "SHORT_BIAS",
        "direction": "SHORT",
        "components": {
          "structure": -0.25,
          "ema": -0.13,
          "cvd": -1,
          "funding": 0.5,
          "oi": 0,
          "delta": -0.5
        },
        "cvdSource": "obv_proxy",
        "liquidityEvent": 1,
        "liquidityType": "wick_reclaim",
        "setupReady15M": 1,
        "confirmed15M": 0,
        "stopLevel": 63461.99,
        "tradeReady15M": 0,
        "mode": "confirmed"
      },
      "_received": "2026-07-05T01:30:04.404Z",
      "_sample": false
    },
    "1H": {
      "symbol": "BTCUSDT",
      "timeframe": "1H",
      "open": 63297.83,
      "high": 63310,
      "low": 63160,
      "close": 63184.99,
      "volume": 486.8775,
      "wickRange": 150,
      "vwap": 62809.4236,
      "ema50": 62313.0111,
      "ema100": null,
      "ema200": 61265.0819,
      "sma50": 62315.5364,
      "sma200": 60548.4403,
      "rsi": 64.6313,
      "stochK": 66.9165,
      "stochD": 74.3693,
      "macdLine": 274.6873,
      "macdHist": 24.7327,
      "atr": 263.6168,
      "volSMA20": 353.7511,
      "bbWidth": 1.9801,
      "trendBias": 0,
      "mfi": 65.74,
      "fracResistance": 63461.99,
      "fracSupport": 62415.87,
      "fracResActive": 1,
      "fracSupActive": 1,
      "fvgBullActive": 0,
      "fvgBullLo": 62968.29,
      "fvgBullHi": 63092.02,
      "fvgBearActive": 0,
      "fvgBearLo": 62559.43,
      "fvgBearHi": 62590.06,
      "coffinFormed": 0,
      "coffinHi": null,
      "coffinLo": null,
      "coffinArmed": 0,
      "coffinBreakLong": 0,
      "coffinBreakShort": 0,
      "coffinAtLevel": 0,
      "ewCount": 0,
      "ewDirection": 1,
      "ewWaveType": "UNKNOWN",
      "ewCorrPattern": "NONE",
      "ewInvalidated": 0,
      "ewBWave": 0,
      "ewDivergence": 0,
      "ewAlternation": "NONE",
      "ewFibTarget": null,
      "ewFibRetrace": null,
      "ewPriorW4High": null,
      "ewPriorW4Low": null,
      "dailyHigh": null,
      "dailyLow": null,
      "dailyOpenHour": null,
      "dailyOpenSession": null,
      "emaStackAligned": 1,
      "volRegime": "NEUTRAL",
      "choch": 0,
      "chochLevel": null,
      "rsiDivBearish": 0,
      "rsiDivBullish": 0,
      "macdDivBearish": 1,
      "macdDivBullish": 0,
      "bosVolConfirmed": 0,
      "bosVolRatio": 1.38,
      "candleType": "NEUTRAL",
      "consolidationForming": 0,
      "consolidationBars": 0,
      "obActive": 0,
      "obType": null,
      "obHigh": null,
      "obLow": null,
      "marketState": null,
      "bdkb": {
        "score": 35,
        "longScore": 35,
        "shortScore": 0,
        "state": "NEUTRAL",
        "direction": "NEUTRAL",
        "components": {
          "structure": 1,
          "ema": 1,
          "cvd": 0,
          "funding": -0.5,
          "oi": -0.5,
          "delta": -1
        },
        "cvdSource": "obv_proxy",
        "liquidityEvent": 0,
        "liquidityType": "none",
        "setupReady1H": 0,
        "confirmed1H": 0,
        "pppSource": "derived",
        "stopLevel": null,
        "tradeReady1H": 0,
        "bdkbScore1HPrev1": 70,
        "bdkbScore1HPrev2": 45,
        "mode": "confirmed"
      },
      "_received": "2026-07-04T23:00:04.141Z",
      "_sample": false,
      "funding": {
        "fundingRate": 0.0001,
        "fundingRatePct": "0.0100%",
        "fundingZone": "ELEVATED",
        "fundingSource": "OKX",
        "nextFundingTime": "1783238400000",
        "conflictLong": false,
        "conflictShort": false,
        "confluenceLong": false,
        "confluenceShort": false,
        "_fetched": "2026-07-04T23:00:04.298Z"
      }
    },
    "30M": {
      "symbol": "BTCUSDT",
      "timeframe": "30M",
      "open": 62991.3,
      "high": 63043.15,
      "low": 62838,
      "close": 62940.04,
      "volume": 242.7024,
      "wickRange": 205.15,
      "vwap": 62989.3508,
      "ema50": 62817.6393,
      "ema100": null,
      "ema200": 61686.7656,
      "sma50": null,
      "sma200": null,
      "rsi": 46.8139,
      "stochK": 0,
      "stochD": 1.6069,
      "macdLine": 79.1629,
      "macdHist": -54.9966,
      "atr": 184.6515,
      "volSMA20": 217.9773,
      "bbWidth": 0.9889,
      "trendBias": 0,
      "mfi": null,
      "fracResistance": null,
      "fracSupport": null,
      "fracResActive": 0,
      "fracSupActive": 0,
      "fvgBullActive": 0,
      "fvgBullLo": null,
      "fvgBullHi": null,
      "fvgBearActive": 0,
      "fvgBearLo": null,
      "fvgBearHi": null,
      "coffinFormed": 0,
      "coffinHi": null,
      "coffinLo": null,
      "coffinArmed": 0,
      "coffinBreakLong": 0,
      "coffinBreakShort": 0,
      "coffinAtLevel": 0,
      "ewCount": 0,
      "ewDirection": 1,
      "ewWaveType": "UNKNOWN",
      "ewCorrPattern": "NONE",
      "ewInvalidated": 0,
      "ewBWave": 0,
      "ewDivergence": 0,
      "ewAlternation": "NONE",
      "ewFibTarget": null,
      "ewFibRetrace": null,
      "ewPriorW4High": null,
      "ewPriorW4Low": null,
      "dailyHigh": null,
      "dailyLow": null,
      "dailyOpenHour": null,
      "dailyOpenSession": null,
      "emaStackAligned": 0,
      "volRegime": "NEUTRAL",
      "choch": 0,
      "chochLevel": null,
      "rsiDivBearish": 0,
      "rsiDivBullish": 0,
      "macdDivBearish": 0,
      "macdDivBullish": 0,
      "bosVolConfirmed": 0,
      "bosVolRatio": null,
      "candleType": null,
      "consolidationForming": 0,
      "consolidationBars": 0,
      "obActive": 0,
      "obType": null,
      "obHigh": null,
      "obLow": null,
      "marketState": null,
      "bdkb": {
        "score": -38,
        "longScore": 0,
        "shortScore": 38,
        "state": "NEUTRAL",
        "direction": "NEUTRAL",
        "components": {
          "structure": -0.25,
          "ema": -0.13,
          "cvd": -1,
          "funding": 0,
          "oi": 0,
          "delta": 0
        },
        "cvdSource": "obv_proxy",
        "liquidityEvent": 0,
        "liquidityType": "none",
        "setupReady30M": 0,
        "confirmed30M": 0,
        "stopLevel": null,
        "tradeReady30M": 0,
        "mode": "confirmed"
      },
      "_received": "2026-07-05T01:30:04.358Z",
      "_sample": false,
      "funding": {
        "fundingRate": 0.0001,
        "fundingRatePct": "0.0100%",
        "fundingZone": "ELEVATED",
        "fundingSource": "OKX",
        "nextFundingTime": "1783267200000",
        "conflictLong": false,
        "conflictShort": false,
        "confluenceLong": false,
        "confluenceShort": false,
        "_fetched": "2026-07-05T01:30:04.508Z"
      }
    },
    "4H": {
      "symbol": "BTCUSDT",
      "timeframe": "4H",
      "open": 62576,
      "high": 62674.47,
      "low": 62415.87,
      "close": 62482.01,
      "volume": 1079.6435,
      "wickRange": 258.6,
      "vwap": 62588.4045,
      "ema50": 61080.2275,
      "ema100": null,
      "ema200": 64089.2235,
      "sma50": null,
      "sma200": null,
      "rsi": 64.9614,
      "stochK": 93.5778,
      "stochD": 97.3119,
      "macdLine": 676.3499,
      "macdHist": 144.1551,
      "atr": 735.7759,
      "volSMA20": 2988.5238,
      "bbWidth": null,
      "trendBias": 0,
      "mfi": 69.19,
      "fracResistance": null,
      "fracSupport": null,
      "fracResActive": 0,
      "fracSupActive": 0,
      "fvgBullActive": 0,
      "fvgBullLo": 62317.64,
      "fvgBullHi": 62404.25,
      "fvgBearActive": 0,
      "fvgBearLo": 58839.16,
      "fvgBearHi": 59123.01,
      "coffinFormed": 0,
      "coffinHi": null,
      "coffinLo": null,
      "coffinArmed": 0,
      "coffinBreakLong": 0,
      "coffinBreakShort": 0,
      "coffinAtLevel": 0,
      "ewCount": 0,
      "ewDirection": 1,
      "ewWaveType": "UNKNOWN",
      "ewCorrPattern": "NONE",
      "ewInvalidated": 0,
      "ewBWave": 0,
      "ewDivergence": 0,
      "ewAlternation": "NONE",
      "ewFibTarget": null,
      "ewFibRetrace": null,
      "ewPriorW4High": null,
      "ewPriorW4Low": null,
      "dailyHigh": null,
      "dailyLow": null,
      "dailyOpenHour": null,
      "dailyOpenSession": null,
      "emaStackAligned": 0,
      "volRegime": "COMPRESSION",
      "choch": 0,
      "chochLevel": null,
      "rsiDivBearish": 0,
      "rsiDivBullish": 1,
      "macdDivBearish": 0,
      "macdDivBullish": 1,
      "bosVolConfirmed": 0,
      "bosVolRatio": 0.36,
      "candleType": "INSIDE_BAR",
      "consolidationForming": 0,
      "consolidationBars": 10,
      "obActive": 0,
      "obType": "NONE",
      "obHigh": null,
      "obLow": null,
      "marketState": null,
      "bdkb": {
        "score": 24,
        "longScore": 24,
        "shortScore": 0,
        "state": "NEUTRAL",
        "direction": "NEUTRAL",
        "components": {
          "structure": 0.5,
          "ema": 0.25,
          "cvd": 0,
          "funding": -0.5,
          "oi": 0
        },
        "cvdSource": "obv_proxy",
        "pppActive": 0,
        "pppSource": "derived",
        "stopLevel": null,
        "tradeReady4H": 0,
        "mode": "confirmed"
      },
      "_received": "2026-07-04T12:00:05.876Z",
      "_sample": false
    }
  },
  "SOLUSDT": {
    "15M": {
      "symbol": "SOLUSDT",
      "timeframe": "15M",
      "open": 81.2,
      "high": 81.21,
      "low": 80.71,
      "close": 81.04,
      "volume": 46615.925,
      "wickRange": 0.5,
      "vwap": 81.2553,
      "ema50": 81.8486,
      "ema100": null,
      "ema200": 81.4235,
      "sma50": null,
      "sma200": null,
      "rsi": 29.2153,
      "stochK": 0,
      "stochD": 0,
      "macdLine": -0.2099,
      "macdHist": -0.0734,
      "atr": 0.2928,
      "volSMA20": 15559.4895,
      "bbWidth": 1.4963,
      "trendBias": -0.5,
      "mfi": 4.65,
      "fracResistance": 81.86,
      "fracSupport": 81.45,
      "fracResActive": 1,
      "fracSupActive": 0,
      "fvgBullActive": 0,
      "fvgBullLo": 82.32,
      "fvgBullHi": 82.4,
      "fvgBearActive": 0,
      "fvgBearLo": 81.47,
      "fvgBearHi": 81.48,
      "coffinFormed": 0,
      "coffinHi": 81.43,
      "coffinLo": 81.3,
      "coffinArmed": 0,
      "coffinBreakLong": 0,
      "coffinBreakShort": 0,
      "coffinAtLevel": 1,
      "ewCount": 0,
      "ewDirection": 1,
      "ewWaveType": "UNKNOWN",
      "ewCorrPattern": "NONE",
      "ewInvalidated": 0,
      "ewBWave": 0,
      "ewDivergence": 0,
      "ewAlternation": "NONE",
      "ewFibTarget": null,
      "ewFibRetrace": null,
      "ewPriorW4High": null,
      "ewPriorW4Low": null,
      "dailyHigh": null,
      "dailyLow": null,
      "dailyOpenHour": null,
      "dailyOpenSession": null,
      "emaStackAligned": 0,
      "volRegime": "NEUTRAL",
      "choch": 0,
      "chochLevel": null,
      "rsiDivBearish": 0,
      "rsiDivBullish": 0,
      "macdDivBearish": 0,
      "macdDivBullish": 0,
      "bosVolConfirmed": 0,
      "bosVolRatio": null,
      "candleType": null,
      "consolidationForming": 0,
      "consolidationBars": 0,
      "obActive": 0,
      "obType": null,
      "obHigh": null,
      "obLow": null,
      "marketState": null,
      "bdkb": {
        "score": -49,
        "longScore": 0,
        "shortScore": 49,
        "state": "SHORT_BIAS",
        "direction": "SHORT",
        "components": {
          "structure": -1,
          "ema": -0.25,
          "cvd": -1,
          "funding": 1,
          "oi": 0.5,
          "delta": -0.5
        },
        "cvdSource": "obv_proxy",
        "liquidityEvent": 1,
        "liquidityType": "wick_reclaim",
        "setupReady15M": 1,
        "confirmed15M": 0,
        "stopLevel": 82.83,
        "tradeReady15M": 0,
        "mode": "confirmed"
      },
      "_received": "2026-07-05T01:30:05.196Z",
      "_sample": false
    },
    "30M": {
      "symbol": "SOLUSDT",
      "timeframe": "30M",
      "open": 81.8,
      "high": 81.84,
      "low": 81.3,
      "close": 81.44,
      "volume": 31208.539,
      "wickRange": 0.54,
      "vwap": 81.5267,
      "ema50": 81.9593,
      "ema100": null,
      "ema200": 79.759,
      "sma50": null,
      "sma200": null,
      "rsi": 37.8137,
      "stochK": 8.2204,
      "stochD": 15.2244,
      "macdLine": -0.1071,
      "macdHist": -0.0482,
      "atr": 0.3884,
      "volSMA20": 30032.7044,
      "bbWidth": 1.2644,
      "trendBias": -1,
      "mfi": null,
      "fracResistance": null,
      "fracSupport": null,
      "fracResActive": 0,
      "fracSupActive": 0,
      "fvgBullActive": 0,
      "fvgBullLo": null,
      "fvgBullHi": null,
      "fvgBearActive": 0,
      "fvgBearLo": null,
      "fvgBearHi": null,
      "coffinFormed": 0,
      "coffinHi": null,
      "coffinLo": null,
      "coffinArmed": 0,
      "coffinBreakLong": 0,
      "coffinBreakShort": 0,
      "coffinAtLevel": 0,
      "ewCount": 0,
      "ewDirection": 1,
      "ewWaveType": "UNKNOWN",
      "ewCorrPattern": "NONE",
      "ewInvalidated": 0,
      "ewBWave": 0,
      "ewDivergence": 0,
      "ewAlternation": "NONE",
      "ewFibTarget": null,
      "ewFibRetrace": null,
      "ewPriorW4High": null,
      "ewPriorW4Low": null,
      "dailyHigh": null,
      "dailyLow": null,
      "dailyOpenHour": null,
      "dailyOpenSession": null,
      "emaStackAligned": 0,
      "volRegime": "NEUTRAL",
      "choch": 0,
      "chochLevel": null,
      "rsiDivBearish": 0,
      "rsiDivBullish": 0,
      "macdDivBearish": 0,
      "macdDivBullish": 0,
      "bosVolConfirmed": 0,
      "bosVolRatio": null,
      "candleType": null,
      "consolidationForming": 0,
      "consolidationBars": 0,
      "obActive": 0,
      "obType": null,
      "obHigh": null,
      "obLow": null,
      "marketState": null,
      "bdkb": {
        "score": -81,
        "longScore": 0,
        "shortScore": 81,
        "state": "STRONG_SHORT",
        "direction": "SHORT",
        "components": {
          "structure": -1,
          "ema": -0.25,
          "cvd": -1,
          "funding": 0.5,
          "oi": -1,
          "delta": -1
        },
        "cvdSource": "obv_proxy",
        "liquidityEvent": 1,
        "liquidityType": "swing_break_reclaim",
        "setupReady30M": 1,
        "confirmed30M": 1,
        "stopLevel": 82.83,
        "tradeReady30M": 1,
        "mode": "confirmed"
      },
      "_received": "2026-07-05T00:30:06.242Z",
      "_sample": false,
      "funding": {
        "fundingRate": 0.0000535078788086,
        "fundingRatePct": "0.0054%",
        "fundingZone": "ELEVATED",
        "fundingSource": "OKX",
        "nextFundingTime": "1783267200000",
        "conflictLong": false,
        "conflictShort": false,
        "confluenceLong": false,
        "confluenceShort": false,
        "_fetched": "2026-07-05T00:30:06.395Z"
      }
    },
    "1H": {
      "symbol": "SOLUSDT",
      "timeframe": "1H",
      "open": 81.8,
      "high": 81.84,
      "low": 81.12,
      "close": 81.3,
      "volume": 69479.951,
      "wickRange": 0.72,
      "vwap": 81.42,
      "ema50": 81.4602,
      "ema100": null,
      "ema200": 77.2083,
      "sma50": 81.8308,
      "sma200": 76.1313,
      "rsi": 40.1784,
      "stochK": 13.4142,
      "stochD": 23.9043,
      "macdLine": -0.0385,
      "macdHist": -0.1025,
      "atr": 0.6027,
      "volSMA20": 72316.2338,
      "bbWidth": 2.2529,
      "trendBias": -0.5,
      "mfi": 51.54,
      "fracResistance": 82.83,
      "fracSupport": 81.58,
      "fracResActive": 1,
      "fracSupActive": 0,
      "fvgBullActive": 0,
      "fvgBullLo": 81.87,
      "fvgBullHi": 82,
      "fvgBearActive": 0,
      "fvgBearLo": 81.94,
      "fvgBearHi": 82.25,
      "coffinFormed": 0,
      "coffinHi": null,
      "coffinLo": null,
      "coffinArmed": 0,
      "coffinBreakLong": 0,
      "coffinBreakShort": 0,
      "coffinAtLevel": 0,
      "ewCount": 0,
      "ewDirection": 1,
      "ewWaveType": "UNKNOWN",
      "ewCorrPattern": "NONE",
      "ewInvalidated": 0,
      "ewBWave": 0,
      "ewDivergence": 0,
      "ewAlternation": "NONE",
      "ewFibTarget": null,
      "ewFibRetrace": null,
      "ewPriorW4High": null,
      "ewPriorW4Low": null,
      "dailyHigh": null,
      "dailyLow": null,
      "dailyOpenHour": null,
      "dailyOpenSession": null,
      "emaStackAligned": 0,
      "volRegime": "NEUTRAL",
      "choch": 0,
      "chochLevel": null,
      "rsiDivBearish": 1,
      "rsiDivBullish": 0,
      "macdDivBearish": 1,
      "macdDivBullish": 0,
      "bosVolConfirmed": 0,
      "bosVolRatio": 0.96,
      "candleType": "NEUTRAL",
      "consolidationForming": 0,
      "consolidationBars": 0,
      "obActive": 0,
      "obType": null,
      "obHigh": null,
      "obLow": null,
      "marketState": null,
      "bdkb": {
        "score": -58,
        "longScore": 0,
        "shortScore": 58,
        "state": "SHORT_BIAS",
        "direction": "SHORT",
        "components": {
          "structure": -1,
          "ema": -0.13,
          "cvd": -1,
          "funding": 0.5,
          "oi": 0,
          "delta": -1
        },
        "cvdSource": "obv_proxy",
        "liquidityEvent": 0,
        "liquidityType": "none",
        "setupReady1H": 0,
        "confirmed1H": 0,
        "pppSource": "derived",
        "stopLevel": 83.98,
        "tradeReady1H": 0,
        "bdkbScore1HPrev1": -30,
        "bdkbScore1HPrev2": -10,
        "mode": "confirmed"
      },
      "_received": "2026-07-05T01:00:06.741Z",
      "_sample": false,
      "funding": {
        "fundingRate": 0.0000573683597843,
        "fundingRatePct": "0.0057%",
        "fundingZone": "ELEVATED",
        "fundingSource": "OKX",
        "nextFundingTime": "1783267200000",
        "conflictLong": false,
        "conflictShort": false,
        "confluenceLong": false,
        "confluenceShort": false,
        "_fetched": "2026-07-05T01:00:06.893Z"
      }
    },
    "4H": {
      "symbol": "SOLUSDT",
      "timeframe": "4H",
      "open": 82.24,
      "high": 82.83,
      "low": 81.71,
      "close": 81.88,
      "volume": 259801.408,
      "wickRange": 1.12,
      "vwap": 82.4322,
      "ema50": 77.0882,
      "ema100": null,
      "ema200": 74.5555,
      "sma50": null,
      "sma200": null,
      "rsi": 63.8043,
      "stochK": 4.6052,
      "stochD": 21.8304,
      "macdLine": 1.9369,
      "macdHist": -0.1717,
      "atr": 1.5742,
      "volSMA20": 461115.6321,
      "bbWidth": null,
      "trendBias": 0.5,
      "mfi": 73.95,
      "fracResistance": null,
      "fracSupport": null,
      "fracResActive": 0,
      "fracSupActive": 0,
      "fvgBullActive": 0,
      "fvgBullLo": 82.06,
      "fvgBullHi": 82.16,
      "fvgBearActive": 0,
      "fvgBearLo": 74.26,
      "fvgBearHi": 74.89,
      "coffinFormed": 0,
      "coffinHi": null,
      "coffinLo": null,
      "coffinArmed": 0,
      "coffinBreakLong": 0,
      "coffinBreakShort": 0,
      "coffinAtLevel": 0,
      "ewCount": 0,
      "ewDirection": 1,
      "ewWaveType": "UNKNOWN",
      "ewCorrPattern": "NONE",
      "ewInvalidated": 0,
      "ewBWave": 0,
      "ewDivergence": 0,
      "ewAlternation": "NONE",
      "ewFibTarget": null,
      "ewFibRetrace": null,
      "ewPriorW4High": null,
      "ewPriorW4Low": null,
      "dailyHigh": null,
      "dailyLow": null,
      "dailyOpenHour": null,
      "dailyOpenSession": null,
      "emaStackAligned": 1,
      "volRegime": "NEUTRAL",
      "choch": 0,
      "chochLevel": null,
      "rsiDivBearish": 0,
      "rsiDivBullish": 0,
      "macdDivBearish": 1,
      "macdDivBullish": 0,
      "bosVolConfirmed": 0,
      "bosVolRatio": 0.56,
      "candleType": "NEUTRAL",
      "consolidationForming": 0,
      "consolidationBars": 3,
      "obActive": 0,
      "obType": "NONE",
      "obHigh": null,
      "obLow": null,
      "marketState": null,
      "bdkb": {
        "score": 43,
        "longScore": 43,
        "shortScore": 0,
        "state": "LONG_BIAS",
        "direction": "LONG",
        "components": {
          "structure": 1,
          "ema": 1,
          "cvd": -1,
          "funding": -0.5,
          "oi": 0
        },
        "cvdSource": "obv_proxy",
        "pppActive": 0,
        "pppSource": "derived",
        "stopLevel": 69.74,
        "tradeReady4H": 0,
        "mode": "confirmed"
      },
      "_received": "2026-07-04T20:00:06.139Z",
      "_sample": false
    }
  },
  "ETHUSDT": {
    "1H": {
      "symbol": "ETHUSDT",
      "timeframe": "1H",
      "open": 1780.64,
      "high": 1780.75,
      "low": 1769.64,
      "close": 1772.71,
      "volume": 6958.1122,
      "wickRange": 11.11,
      "vwap": 1774.3667,
      "ema50": 1746.8169,
      "ema100": null,
      "ema200": 1672.1849,
      "sma50": 1750.2958,
      "sma200": 1634.8267,
      "rsi": 52.682,
      "stochK": 2.9394,
      "stochD": 13.904,
      "macdLine": 10.691,
      "macdHist": -2.1405,
      "atr": 12.02,
      "volSMA20": 8670.9068,
      "bbWidth": 3.3452,
      "trendBias": -0.5,
      "mfi": 68.72,
      "fracResistance": 1807.65,
      "fracSupport": 1751.72,
      "fracResActive": 1,
      "fracSupActive": 1,
      "fvgBullActive": 0,
      "fvgBullLo": 1775,
      "fvgBullHi": 1783.32,
      "fvgBearActive": 0,
      "fvgBearLo": 1780.75,
      "fvgBearHi": 1782.19,
      "coffinFormed": 0,
      "coffinHi": null,
      "coffinLo": null,
      "coffinArmed": 0,
      "coffinBreakLong": 0,
      "coffinBreakShort": 0,
      "coffinAtLevel": 0,
      "ewCount": 0,
      "ewDirection": 1,
      "ewWaveType": "UNKNOWN",
      "ewCorrPattern": "NONE",
      "ewInvalidated": 0,
      "ewBWave": 0,
      "ewDivergence": 0,
      "ewAlternation": "NONE",
      "ewFibTarget": null,
      "ewFibRetrace": null,
      "ewPriorW4High": null,
      "ewPriorW4Low": null,
      "dailyHigh": null,
      "dailyLow": null,
      "dailyOpenHour": null,
      "dailyOpenSession": null,
      "emaStackAligned": 0,
      "volRegime": "NEUTRAL",
      "choch": 0,
      "chochLevel": null,
      "rsiDivBearish": 1,
      "rsiDivBullish": 0,
      "macdDivBearish": 1,
      "macdDivBullish": 0,
      "bosVolConfirmed": 0,
      "bosVolRatio": 0.8,
      "candleType": "NEUTRAL",
      "consolidationForming": 0,
      "consolidationBars": 0,
      "obActive": 0,
      "obType": null,
      "obHigh": null,
      "obLow": null,
      "marketState": null,
      "bdkb": {
        "score": -40,
        "longScore": 0,
        "shortScore": 40,
        "state": "INVALIDATED",
        "direction": "SHORT",
        "components": {
          "structure": -0.25,
          "ema": -0.13,
          "cvd": -1,
          "funding": 0,
          "oi": 0,
          "delta": -1
        },
        "cvdSource": "obv_proxy",
        "liquidityEvent": 1,
        "liquidityType": "swing_break_reclaim",
        "setupReady1H": 1,
        "confirmed1H": 0,
        "pppSource": "derived",
        "stopLevel": 1779.922,
        "tradeReady1H": 0,
        "bdkbScore1HPrev1": 43,
        "bdkbScore1HPrev2": 40,
        "mode": "confirmed"
      },
      "_received": "2026-07-05T01:00:04.631Z",
      "_sample": false,
      "funding": {
        "fundingRate": 0.0000781750381364,
        "fundingRatePct": "0.0078%",
        "fundingZone": "ELEVATED",
        "fundingSource": "OKX",
        "nextFundingTime": "1783267200000",
        "conflictLong": false,
        "conflictShort": false,
        "confluenceLong": false,
        "confluenceShort": false,
        "_fetched": "2026-07-05T01:00:04.788Z"
      }
    },
    "30M": {
      "symbol": "ETHUSDT",
      "timeframe": "30M",
      "open": 1772.7,
      "high": 1774.66,
      "low": 1763.95,
      "close": 1768.71,
      "volume": 5554.6466,
      "wickRange": 10.71,
      "vwap": 1772.0329,
      "ema50": 1770.3816,
      "ema100": null,
      "ema200": 1706.6818,
      "sma50": null,
      "sma200": null,
      "rsi": 39.6732,
      "stochK": 0,
      "stochD": 1.3691,
      "macdLine": 0.8828,
      "macdHist": -3.519,
      "atr": 8.0001,
      "volSMA20": 4756.9501,
      "bbWidth": 1.7609,
      "trendBias": -0.5,
      "mfi": null,
      "fracResistance": null,
      "fracSupport": null,
      "fracResActive": 0,
      "fracSupActive": 0,
      "fvgBullActive": 0,
      "fvgBullLo": null,
      "fvgBullHi": null,
      "fvgBearActive": 0,
      "fvgBearLo": null,
      "fvgBearHi": null,
      "coffinFormed": 0,
      "coffinHi": null,
      "coffinLo": null,
      "coffinArmed": 0,
      "coffinBreakLong": 0,
      "coffinBreakShort": 0,
      "coffinAtLevel": 0,
      "ewCount": 0,
      "ewDirection": 1,
      "ewWaveType": "UNKNOWN",
      "ewCorrPattern": "NONE",
      "ewInvalidated": 0,
      "ewBWave": 0,
      "ewDivergence": 0,
      "ewAlternation": "NONE",
      "ewFibTarget": null,
      "ewFibRetrace": null,
      "ewPriorW4High": null,
      "ewPriorW4Low": null,
      "dailyHigh": null,
      "dailyLow": null,
      "dailyOpenHour": null,
      "dailyOpenSession": null,
      "emaStackAligned": 0,
      "volRegime": "NEUTRAL",
      "choch": 0,
      "chochLevel": null,
      "rsiDivBearish": 0,
      "rsiDivBullish": 0,
      "macdDivBearish": 0,
      "macdDivBullish": 0,
      "bosVolConfirmed": 0,
      "bosVolRatio": null,
      "candleType": null,
      "consolidationForming": 0,
      "consolidationBars": 0,
      "obActive": 0,
      "obType": null,
      "obHigh": null,
      "obLow": null,
      "marketState": null,
      "bdkb": {
        "score": -41,
        "longScore": 0,
        "shortScore": 41,
        "state": "SHORT_BIAS",
        "direction": "SHORT",
        "components": {
          "structure": -0.25,
          "ema": -0.13,
          "cvd": -1,
          "funding": 0.5,
          "oi": 0,
          "delta": -0.5
        },
        "cvdSource": "obv_proxy",
        "liquidityEvent": 0,
        "liquidityType": "none",
        "setupReady30M": 0,
        "confirmed30M": 0,
        "stopLevel": 1807.65,
        "tradeReady30M": 0,
        "mode": "confirmed"
      },
      "_received": "2026-07-05T01:30:05.661Z",
      "_sample": false,
      "funding": {
        "fundingRate": 0.0000659372528084,
        "fundingRatePct": "0.0066%",
        "fundingZone": "ELEVATED",
        "fundingSource": "OKX",
        "nextFundingTime": "1783267200000",
        "conflictLong": false,
        "conflictShort": false,
        "confluenceLong": false,
        "confluenceShort": false,
        "_fetched": "2026-07-05T01:30:05.812Z"
      }
    },
    "15M": {
      "symbol": "ETHUSDT",
      "timeframe": "15M",
      "open": 1771.65,
      "high": 1771.66,
      "low": 1763.95,
      "close": 1768.71,
      "volume": 4024.4806,
      "wickRange": 7.71,
      "vwap": 1772.2481,
      "ema50": 1779.5283,
      "ema100": null,
      "ema200": 1746.7809,
      "sma50": null,
      "sma200": null,
      "rsi": 33.7733,
      "stochK": 0.6407,
      "stochD": 6.2157,
      "macdLine": -3.9083,
      "macdHist": -1.7486,
      "atr": 5.5578,
      "volSMA20": 1464.4461,
      "bbWidth": 1.5711,
      "trendBias": -0.5,
      "mfi": 6.23,
      "fracResistance": 1794.25,
      "fracSupport": 1772.1,
      "fracResActive": 1,
      "fracSupActive": 0,
      "fvgBullActive": 0,
      "fvgBullLo": 1778.87,
      "fvgBullHi": 1779.06,
      "fvgBearActive": 0,
      "fvgBearLo": 1776.7,
      "fvgBearHi": 1779.06,
      "coffinFormed": 0,
      "coffinHi": 1775.82,
      "coffinLo": 1772.71,
      "coffinArmed": 0,
      "coffinBreakLong": 0,
      "coffinBreakShort": 0,
      "coffinAtLevel": 1,
      "ewCount": 0,
      "ewDirection": 1,
      "ewWaveType": "UNKNOWN",
      "ewCorrPattern": "NONE",
      "ewInvalidated": 0,
      "ewBWave": 0,
      "ewDivergence": 0,
      "ewAlternation": "NONE",
      "ewFibTarget": null,
      "ewFibRetrace": null,
      "ewPriorW4High": null,
      "ewPriorW4Low": null,
      "dailyHigh": null,
      "dailyLow": null,
      "dailyOpenHour": null,
      "dailyOpenSession": null,
      "emaStackAligned": 0,
      "volRegime": "NEUTRAL",
      "choch": 0,
      "chochLevel": null,
      "rsiDivBearish": 0,
      "rsiDivBullish": 0,
      "macdDivBearish": 0,
      "macdDivBullish": 0,
      "bosVolConfirmed": 0,
      "bosVolRatio": null,
      "candleType": null,
      "consolidationForming": 0,
      "consolidationBars": 0,
      "obActive": 0,
      "obType": null,
      "obHigh": null,
      "obLow": null,
      "marketState": null,
      "bdkb": {
        "score": -57,
        "longScore": 0,
        "shortScore": 57,
        "state": "SHORT_BIAS",
        "direction": "SHORT",
        "components": {
          "structure": -1,
          "ema": -0.13,
          "cvd": -1,
          "funding": 0.5,
          "oi": 0,
          "delta": -0.5
        },
        "cvdSource": "obv_proxy",
        "liquidityEvent": 1,
        "liquidityType": "wick_reclaim",
        "setupReady15M": 1,
        "confirmed15M": 0,
        "stopLevel": 1807.65,
        "tradeReady15M": 0,
        "mode": "confirmed"
      },
      "_received": "2026-07-05T01:30:05.421Z",
      "_sample": false
    },
    "4H": {
      "symbol": "ETHUSDT",
      "timeframe": "4H",
      "open": 1791.08,
      "high": 1807.65,
      "low": 1779,
      "close": 1792.83,
      "volume": 55311.175,
      "wickRange": 28.65,
      "vwap": 1776.7846,
      "ema50": 1668.5131,
      "ema100": null,
      "ema200": 1736.1008,
      "sma50": null,
      "sma200": null,
      "rsi": 76.7953,
      "stochK": 98.3758,
      "stochD": 96.3856,
      "macdLine": 45.3419,
      "macdHist": 6.6715,
      "atr": 28.4111,
      "volSMA20": 48964.1823,
      "bbWidth": null,
      "trendBias": 0.5,
      "mfi": 97.01,
      "fracResistance": null,
      "fracSupport": null,
      "fracResActive": 0,
      "fracSupActive": 0,
      "fvgBullActive": 0,
      "fvgBullLo": 1765.55,
      "fvgBullHi": 1779,
      "fvgBearActive": 0,
      "fvgBearLo": 1578.58,
      "fvgBearHi": 1579.79,
      "coffinFormed": 0,
      "coffinHi": null,
      "coffinLo": null,
      "coffinArmed": 0,
      "coffinBreakLong": 0,
      "coffinBreakShort": 0,
      "coffinAtLevel": 0,
      "ewCount": 0,
      "ewDirection": 1,
      "ewWaveType": "UNKNOWN",
      "ewCorrPattern": "NONE",
      "ewInvalidated": 0,
      "ewBWave": 0,
      "ewDivergence": 0,
      "ewAlternation": "NONE",
      "ewFibTarget": null,
      "ewFibRetrace": null,
      "ewPriorW4High": null,
      "ewPriorW4Low": null,
      "dailyHigh": null,
      "dailyLow": null,
      "dailyOpenHour": null,
      "dailyOpenSession": null,
      "emaStackAligned": 0,
      "volRegime": "NEUTRAL",
      "choch": 0,
      "chochLevel": null,
      "rsiDivBearish": 0,
      "rsiDivBullish": 0,
      "macdDivBearish": 0,
      "macdDivBullish": 0,
      "bosVolConfirmed": 0,
      "bosVolRatio": 1.13,
      "candleType": "DOJI",
      "consolidationForming": 0,
      "consolidationBars": 0,
      "obActive": 1,
      "obType": "BULL",
      "obHigh": 1639.46,
      "obLow": 1615.97,
      "marketState": null,
      "bdkb": {
        "score": 61,
        "longScore": 61,
        "shortScore": 0,
        "state": "LONG_BIAS",
        "direction": "LONG",
        "components": {
          "structure": 1,
          "ema": 0.25,
          "cvd": 1,
          "funding": -1,
          "oi": 0
        },
        "cvdSource": "obv_proxy",
        "pppActive": 0,
        "pppSource": "derived",
        "stopLevel": 1548.37,
        "tradeReady4H": 0,
        "mode": "confirmed"
      },
      "_received": "2026-07-04T20:00:05.147Z",
      "_sample": false
    }
  },
  "SUIUSDT": {
    "30M": {
      "symbol": "SUIUSDT",
      "timeframe": "30M",
      "open": 0.7738,
      "high": 0.774,
      "low": 0.7705,
      "close": 0.7709,
      "volume": 383148.8,
      "wickRange": 0.0035,
      "vwap": 0.7658,
      "ema50": 0.7627,
      "ema100": null,
      "ema200": 0.7394,
      "sma50": null,
      "sma200": null,
      "rsi": 56.1452,
      "stochK": 37.6628,
      "stochD": 55.7959,
      "macdLine": 0.0042,
      "macdHist": 0.0008,
      "atr": 0.0053,
      "volSMA20": 490627.745,
      "bbWidth": 4.2496,
      "trendBias": 0,
      "mfi": null,
      "fracResistance": null,
      "fracSupport": null,
      "fracResActive": 0,
      "fracSupActive": 0,
      "fvgBullActive": 0,
      "fvgBullLo": null,
      "fvgBullHi": null,
      "fvgBearActive": 0,
      "fvgBearLo": null,
      "fvgBearHi": null,
      "coffinFormed": 0,
      "coffinHi": null,
      "coffinLo": null,
      "coffinArmed": 0,
      "coffinBreakLong": 0,
      "coffinBreakShort": 0,
      "coffinAtLevel": 0,
      "ewCount": 0,
      "ewDirection": 1,
      "ewWaveType": "UNKNOWN",
      "ewCorrPattern": "NONE",
      "ewInvalidated": 0,
      "ewBWave": 0,
      "ewDivergence": 0,
      "ewAlternation": "NONE",
      "ewFibTarget": null,
      "ewFibRetrace": null,
      "ewPriorW4High": null,
      "ewPriorW4Low": null,
      "dailyHigh": null,
      "dailyLow": null,
      "dailyOpenHour": null,
      "dailyOpenSession": null,
      "emaStackAligned": 1,
      "volRegime": "NEUTRAL",
      "choch": 0,
      "chochLevel": null,
      "rsiDivBearish": 0,
      "rsiDivBullish": 0,
      "macdDivBearish": 0,
      "macdDivBullish": 0,
      "bosVolConfirmed": 0,
      "bosVolRatio": null,
      "candleType": null,
      "consolidationForming": 0,
      "consolidationBars": 0,
      "obActive": 0,
      "obType": null,
      "obHigh": null,
      "obLow": null,
      "marketState": null,
      "bdkb": {
        "score": 9,
        "longScore": 9,
        "shortScore": 0,
        "state": "NEUTRAL",
        "direction": "NEUTRAL",
        "components": {
          "structure": 0.25,
          "ema": 1,
          "cvd": 0,
          "funding": -0.5,
          "oi": 0,
          "delta": -1
        },
        "cvdSource": "obv_proxy",
        "liquidityEvent": 0,
        "liquidityType": "none",
        "setupReady30M": 0,
        "confirmed30M": 0,
        "stopLevel": null,
        "tradeReady30M": 0,
        "mode": "confirmed"
      },
      "_received": "2026-07-04T20:00:10.185Z",
      "_sample": false,
      "funding": {
        "fundingRate": 0.0001,
        "fundingRatePct": "0.0100%",
        "fundingZone": "ELEVATED",
        "fundingSource": "OKX",
        "nextFundingTime": "1783238400000",
        "conflictLong": false,
        "conflictShort": false,
        "confluenceLong": false,
        "confluenceShort": false,
        "_fetched": "2026-07-04T20:00:10.336Z"
      }
    },
    "15M": {
      "symbol": "SUIUSDT",
      "timeframe": "15M",
      "open": 0.7527,
      "high": 0.7547,
      "low": 0.7516,
      "close": 0.7519,
      "volume": 605023.4,
      "wickRange": 0.0031,
      "vwap": 0.7543,
      "ema50": 0.7653,
      "ema100": null,
      "ema200": 0.7561,
      "sma50": null,
      "sma200": null,
      "rsi": 26.4859,
      "stochK": 0,
      "stochD": 0,
      "macdLine": -0.0041,
      "macdHist": -0.0018,
      "atr": 0.0041,
      "volSMA20": 287864.16,
      "bbWidth": 3.4165,
      "trendBias": -0.5,
      "mfi": 0,
      "fracResistance": 0.7759,
      "fracSupport": 0.7655,
      "fracResActive": 1,
      "fracSupActive": 0,
      "fvgBullActive": 0,
      "fvgBullLo": 0.7713,
      "fvgBullHi": 0.7727,
      "fvgBearActive": 0,
      "fvgBearLo": 0.7577,
      "fvgBearHi": 0.758,
      "coffinFormed": 0,
      "coffinHi": 0.7654,
      "coffinLo": 0.7637,
      "coffinArmed": 0,
      "coffinBreakLong": 0,
      "coffinBreakShort": 0,
      "coffinAtLevel": 0,
      "ewCount": 0,
      "ewDirection": 1,
      "ewWaveType": "UNKNOWN",
      "ewCorrPattern": "NONE",
      "ewInvalidated": 0,
      "ewBWave": 0,
      "ewDivergence": 0,
      "ewAlternation": "NONE",
      "ewFibTarget": null,
      "ewFibRetrace": null,
      "ewPriorW4High": null,
      "ewPriorW4Low": null,
      "dailyHigh": null,
      "dailyLow": null,
      "dailyOpenHour": null,
      "dailyOpenSession": null,
      "emaStackAligned": 0,
      "volRegime": "NEUTRAL",
      "choch": 0,
      "chochLevel": null,
      "rsiDivBearish": 0,
      "rsiDivBullish": 0,
      "macdDivBearish": 0,
      "macdDivBullish": 0,
      "bosVolConfirmed": 0,
      "bosVolRatio": null,
      "candleType": null,
      "consolidationForming": 0,
      "consolidationBars": 0,
      "obActive": 0,
      "obType": null,
      "obHigh": null,
      "obLow": null,
      "marketState": null,
      "bdkb": {
        "score": -64,
        "longScore": 0,
        "shortScore": 64,
        "state": "SHORT_BIAS",
        "direction": "SHORT",
        "components": {
          "structure": -1,
          "ema": -0.25,
          "cvd": -1,
          "funding": 1,
          "oi": -1,
          "delta": 0
        },
        "cvdSource": "obv_proxy",
        "liquidityEvent": 1,
        "liquidityType": "wick_reclaim",
        "setupReady15M": 1,
        "confirmed15M": 0,
        "stopLevel": 0.7791,
        "tradeReady15M": 0,
        "mode": "confirmed"
      },
      "_received": "2026-07-05T01:15:04.232Z",
      "_sample": false
    },
    "1H": {
      "symbol": "SUIUSDT",
      "timeframe": "1H",
      "open": 0.7157,
      "high": 0.717,
      "low": 0.7102,
      "close": 0.7157,
      "volume": 1153202.7,
      "wickRange": 0.0068,
      "vwap": 0.7143,
      "ema50": 0.7031,
      "ema100": null,
      "ema200": 0.7002,
      "sma50": 0.7,
      "sma200": 0.6927,
      "rsi": 57.7737,
      "stochK": 53.9744,
      "stochD": 72.8175,
      "macdLine": 0.0058,
      "macdHist": 0.0005,
      "atr": 0.0082,
      "volSMA20": 1191577.895,
      "bbWidth": 4.8991,
      "trendBias": 0.5,
      "mfi": 64.59,
      "fracResistance": 0.7302,
      "fracSupport": 0.7099,
      "fracResActive": 1,
      "fracSupActive": 1,
      "fvgBullActive": 0,
      "fvgBullLo": 0.7161,
      "fvgBullHi": 0.7219,
      "fvgBearActive": 0,
      "fvgBearLo": 0.717,
      "fvgBearHi": 0.7219,
      "coffinFormed": 0,
      "coffinHi": null,
      "coffinLo": null,
      "coffinArmed": 0,
      "coffinBreakLong": 0,
      "coffinBreakShort": 0,
      "coffinAtLevel": 0,
      "ewCount": 0,
      "ewDirection": 1,
      "ewWaveType": "UNKNOWN",
      "ewCorrPattern": "NONE",
      "ewInvalidated": 0,
      "ewBWave": 0,
      "ewDivergence": 0,
      "ewAlternation": "NONE",
      "ewFibTarget": null,
      "ewFibRetrace": null,
      "ewPriorW4High": null,
      "ewPriorW4Low": null,
      "dailyHigh": null,
      "dailyLow": null,
      "dailyOpenHour": null,
      "dailyOpenSession": null,
      "emaStackAligned": 1,
      "volRegime": "NEUTRAL",
      "choch": 0,
      "chochLevel": null,
      "rsiDivBearish": 0,
      "rsiDivBullish": 0,
      "macdDivBearish": 0,
      "macdDivBullish": 0,
      "bosVolConfirmed": 0,
      "bosVolRatio": 0.97,
      "candleType": "PIN_BULL",
      "consolidationForming": 0,
      "consolidationBars": 0,
      "obActive": 0,
      "obType": null,
      "obHigh": null,
      "obLow": null,
      "marketState": null,
      "bdkb": {
        "score": 58,
        "longScore": 58,
        "shortScore": 0,
        "state": "LONG_BIAS",
        "direction": "LONG",
        "components": {
          "structure": 1,
          "ema": 1,
          "cvd": 0.5,
          "funding": -0.5,
          "oi": 0,
          "delta": 0
        },
        "cvdSource": "obv_proxy",
        "liquidityEvent": 1,
        "liquidityType": "wick_reclaim",
        "setupReady1H": 1,
        "confirmed1H": 0,
        "pppSource": "derived",
        "stopLevel": 0.6778,
        "tradeReady1H": 0,
        "bdkbScore1HPrev1": 40,
        "bdkbScore1HPrev2": 35,
        "mode": "confirmed"
      },
      "_received": "2026-07-02T01:00:14.033Z",
      "_sample": false,
      "funding": {
        "fundingRate": 0.0000938404840247,
        "fundingRatePct": "0.0094%",
        "fundingZone": "ELEVATED",
        "fundingSource": "OKX",
        "nextFundingTime": "1783008000000",
        "conflictLong": false,
        "conflictShort": false,
        "confluenceLong": false,
        "confluenceShort": false,
        "_fetched": "2026-07-02T01:00:14.217Z"
      }
    },
    "4H": {
      "symbol": "SUIUSDT",
      "timeframe": "4H",
      "open": 0.9096,
      "high": 0.9158,
      "low": 0.9043,
      "close": 0.91,
      "volume": 2759161.5,
      "wickRange": 0.0115,
      "vwap": 0.9054,
      "ema50": 0.9791,
      "ema100": null,
      "ema200": 1.021,
      "sma50": null,
      "sma200": null,
      "rsi": 35.0079,
      "stochK": 84.0517,
      "stochD": 71.0767,
      "macdLine": -0.0268,
      "macdHist": 0.0028,
      "atr": 0.0229,
      "volSMA20": 9864628.87,
      "bbWidth": null,
      "trendBias": -0.5,
      "mfi": 42.13,
      "fracResistance": null,
      "fracSupport": null,
      "fracResActive": 0,
      "fracSupActive": 0,
      "fvgBullActive": 0,
      "fvgBullLo": 0.9037,
      "fvgBullHi": 0.9043,
      "fvgBearActive": 0,
      "fvgBearLo": 0.9274,
      "fvgBearHi": 0.9539,
      "coffinFormed": 0,
      "coffinHi": null,
      "coffinLo": null,
      "coffinArmed": 0,
      "coffinBreakLong": 0,
      "coffinBreakShort": 0,
      "coffinAtLevel": 0,
      "ewCount": 0,
      "ewDirection": 1,
      "ewWaveType": "UNKNOWN",
      "ewCorrPattern": "NONE",
      "ewInvalidated": 0,
      "ewBWave": 0,
      "ewDivergence": 0,
      "ewAlternation": "NONE",
      "ewFibTarget": null,
      "ewFibRetrace": null,
      "ewPriorW4High": null,
      "ewPriorW4Low": null,
      "dailyHigh": null,
      "dailyLow": null,
      "dailyOpenHour": null,
      "dailyOpenSession": null,
      "emaStackAligned": 1,
      "volRegime": "COMPRESSION",
      "choch": 0,
      "chochLevel": null,
      "rsiDivBearish": 0,
      "rsiDivBullish": 1,
      "macdDivBearish": 0,
      "macdDivBullish": 0,
      "bosVolConfirmed": 0,
      "bosVolRatio": 0.28,
      "candleType": "DOJI",
      "consolidationForming": 0,
      "consolidationBars": 6,
      "obActive": 0,
      "obType": "NONE",
      "obHigh": null,
      "obLow": null,
      "marketState": null,
      "bdkb": {
        "score": -43,
        "longScore": 0,
        "shortScore": 43,
        "state": "SHORT_BIAS",
        "direction": "SHORT",
        "components": {
          "structure": -1,
          "ema": -1,
          "cvd": 1,
          "funding": 0.5,
          "oi": 0
        },
        "cvdSource": "obv_proxy",
        "pppActive": 0,
        "pppSource": "derived",
        "stopLevel": 1.165,
        "tradeReady4H": 0,
        "mode": "confirmed"
      },
      "_received": "2026-05-30T20:00:06.839Z",
      "_sample": false
    }
  },
  "ADAUSDT": {
    "15M": {
      "symbol": "ADAUSDT",
      "timeframe": "15M",
      "open": 0.1932,
      "high": 0.1952,
      "low": 0.1928,
      "close": 0.1929,
      "volume": 8672612.2,
      "wickRange": 0.0024,
      "vwap": 0.1928,
      "ema50": 0.19,
      "ema100": null,
      "ema200": 0.1786,
      "sma50": null,
      "sma200": null,
      "rsi": 53.6187,
      "stochK": 64.7165,
      "stochD": 59.4032,
      "macdLine": 0.0004,
      "macdHist": -0.0001,
      "atr": 0.0018,
      "volSMA20": 2309898.825,
      "bbWidth": 1.3836,
      "trendBias": 0,
      "mfi": 67.37,
      "fracResistance": 0.1936,
      "fracSupport": 0.1893,
      "fracResActive": 1,
      "fracSupActive": 1,
      "fvgBullActive": 0,
      "fvgBullLo": 0.1927,
      "fvgBullHi": 0.1928,
      "fvgBearActive": 0,
      "fvgBearLo": 0.1924,
      "fvgBearHi": 0.1931,
      "coffinFormed": 1,
      "coffinHi": 0.1932,
      "coffinLo": 0.1924,
      "coffinArmed": 1,
      "coffinBreakLong": 0,
      "coffinBreakShort": 0,
      "coffinAtLevel": 1,
      "ewCount": 0,
      "ewDirection": 1,
      "ewWaveType": "UNKNOWN",
      "ewCorrPattern": "NONE",
      "ewInvalidated": 0,
      "ewBWave": 0,
      "ewDivergence": 0,
      "ewAlternation": "NONE",
      "ewFibTarget": null,
      "ewFibRetrace": null,
      "ewPriorW4High": null,
      "ewPriorW4Low": null,
      "dailyHigh": null,
      "dailyLow": null,
      "dailyOpenHour": null,
      "dailyOpenSession": null,
      "emaStackAligned": 1,
      "volRegime": "NEUTRAL",
      "choch": 0,
      "chochLevel": null,
      "rsiDivBearish": 0,
      "rsiDivBullish": 0,
      "macdDivBearish": 0,
      "macdDivBullish": 0,
      "bosVolConfirmed": 0,
      "bosVolRatio": null,
      "candleType": null,
      "consolidationForming": 0,
      "consolidationBars": 0,
      "obActive": 0,
      "obType": null,
      "obHigh": null,
      "obLow": null,
      "marketState": null,
      "bdkb": {
        "score": 5,
        "longScore": 5,
        "shortScore": 0,
        "state": "NEUTRAL",
        "direction": "NEUTRAL",
        "components": {
          "structure": 0.25,
          "ema": 1,
          "cvd": 0,
          "funding": 0,
          "oi": -1,
          "delta": 0
        },
        "cvdSource": "obv_proxy",
        "liquidityEvent": 1,
        "liquidityType": "wick_reclaim",
        "setupReady15M": 0,
        "confirmed15M": 0,
        "stopLevel": null,
        "tradeReady15M": 0,
        "mode": "confirmed"
      },
      "_received": "2026-07-05T01:15:03.298Z",
      "_sample": false
    },
    "30M": {
      "symbol": "ADAUSDT",
      "timeframe": "30M",
      "open": 0.1921,
      "high": 0.1929,
      "low": 0.1917,
      "close": 0.1922,
      "volume": 2791169.5,
      "wickRange": 0.0012,
      "vwap": 0.1882,
      "ema50": 0.1849,
      "ema100": null,
      "ema200": 0.1691,
      "sma50": null,
      "sma200": null,
      "rsi": 59.0819,
      "stochK": 7.9568,
      "stochD": 6.0868,
      "macdLine": 0.0027,
      "macdHist": -0.0008,
      "atr": 0.0025,
      "volSMA20": 11353280.58,
      "bbWidth": 8.7228,
      "trendBias": 0.5,
      "mfi": null,
      "fracResistance": null,
      "fracSupport": null,
      "fracResActive": 0,
      "fracSupActive": 0,
      "fvgBullActive": 0,
      "fvgBullLo": null,
      "fvgBullHi": null,
      "fvgBearActive": 0,
      "fvgBearLo": null,
      "fvgBearHi": null,
      "coffinFormed": 0,
      "coffinHi": null,
      "coffinLo": null,
      "coffinArmed": 0,
      "coffinBreakLong": 0,
      "coffinBreakShort": 0,
      "coffinAtLevel": 0,
      "ewCount": 0,
      "ewDirection": 1,
      "ewWaveType": "UNKNOWN",
      "ewCorrPattern": "NONE",
      "ewInvalidated": 0,
      "ewBWave": 0,
      "ewDivergence": 0,
      "ewAlternation": "NONE",
      "ewFibTarget": null,
      "ewFibRetrace": null,
      "ewPriorW4High": null,
      "ewPriorW4Low": null,
      "dailyHigh": null,
      "dailyLow": null,
      "dailyOpenHour": null,
      "dailyOpenSession": null,
      "emaStackAligned": 1,
      "volRegime": "NEUTRAL",
      "choch": 0,
      "chochLevel": null,
      "rsiDivBearish": 0,
      "rsiDivBullish": 0,
      "macdDivBearish": 0,
      "macdDivBullish": 0,
      "bosVolConfirmed": 0,
      "bosVolRatio": null,
      "candleType": null,
      "consolidationForming": 0,
      "consolidationBars": 0,
      "obActive": 0,
      "obType": null,
      "obHigh": null,
      "obLow": null,
      "marketState": null,
      "bdkb": {
        "score": 49,
        "longScore": 49,
        "shortScore": 0,
        "state": "LONG_BIAS",
        "direction": "LONG",
        "components": {
          "structure": 0.25,
          "ema": 1,
          "cvd": 1,
          "funding": -0.5,
          "oi": 0,
          "delta": 0
        },
        "cvdSource": "obv_proxy",
        "liquidityEvent": 0,
        "liquidityType": "none",
        "setupReady30M": 0,
        "confirmed30M": 0,
        "stopLevel": 0.175,
        "tradeReady30M": 0,
        "mode": "confirmed"
      },
      "_received": "2026-07-05T00:00:14.999Z",
      "_sample": false,
      "funding": {
        "fundingRate": 0.0000979394958557,
        "fundingRatePct": "0.0098%",
        "fundingZone": "ELEVATED",
        "fundingSource": "OKX",
        "nextFundingTime": "1783267200000",
        "conflictLong": false,
        "conflictShort": false,
        "confluenceLong": false,
        "confluenceShort": false,
        "_fetched": "2026-07-05T00:00:15.150Z"
      }
    },
    "1H": {
      "symbol": "ADAUSDT",
      "timeframe": "1H",
      "open": 0.1921,
      "high": 0.1936,
      "low": 0.1893,
      "close": 0.1931,
      "volume": 14637497.8,
      "wickRange": 0.0043,
      "vwap": 0.192,
      "ema50": 0.1787,
      "ema100": null,
      "ema200": 0.1621,
      "sma50": 0.1775,
      "sma200": 0.1558,
      "rsi": 66.6074,
      "stochK": 35.5251,
      "stochD": 37.028,
      "macdLine": 0.005,
      "macdHist": 0.0001,
      "atr": 0.0035,
      "volSMA20": 14781949.7,
      "bbWidth": 18.1602,
      "trendBias": 1,
      "mfi": 84.73,
      "fracResistance": 0.2,
      "fracSupport": 0.175,
      "fracResActive": 1,
      "fracSupActive": 1,
      "fvgBullActive": 0,
      "fvgBullLo": 0.192,
      "fvgBullHi": 0.1936,
      "fvgBearActive": 0,
      "fvgBearLo": 0.1769,
      "fvgBearHi": 0.1773,
      "coffinFormed": 0,
      "coffinHi": null,
      "coffinLo": null,
      "coffinArmed": 0,
      "coffinBreakLong": 0,
      "coffinBreakShort": 0,
      "coffinAtLevel": 0,
      "ewCount": 0,
      "ewDirection": 1,
      "ewWaveType": "UNKNOWN",
      "ewCorrPattern": "NONE",
      "ewInvalidated": 0,
      "ewBWave": 0,
      "ewDivergence": 0,
      "ewAlternation": "NONE",
      "ewFibTarget": null,
      "ewFibRetrace": null,
      "ewPriorW4High": null,
      "ewPriorW4Low": null,
      "dailyHigh": null,
      "dailyLow": null,
      "dailyOpenHour": null,
      "dailyOpenSession": null,
      "emaStackAligned": 1,
      "volRegime": "EXPANSION",
      "choch": 0,
      "chochLevel": null,
      "rsiDivBearish": 0,
      "rsiDivBullish": 0,
      "macdDivBearish": 0,
      "macdDivBullish": 0,
      "bosVolConfirmed": 0,
      "bosVolRatio": 0.99,
      "candleType": "PIN_BULL",
      "consolidationForming": 0,
      "consolidationBars": 0,
      "obActive": 0,
      "obType": null,
      "obHigh": null,
      "obLow": null,
      "marketState": null,
      "bdkb": {
        "score": 70,
        "longScore": 70,
        "shortScore": 0,
        "state": "STRONG_LONG",
        "direction": "LONG",
        "components": {
          "structure": 1,
          "ema": 1,
          "cvd": 1,
          "funding": -0.5,
          "oi": 0,
          "delta": 0
        },
        "cvdSource": "obv_proxy",
        "liquidityEvent": 1,
        "liquidityType": "wick_reclaim",
        "setupReady1H": 1,
        "confirmed1H": 1,
        "pppSource": "derived",
        "stopLevel": 0.175,
        "tradeReady1H": 1,
        "bdkbScore1HPrev1": 45,
        "bdkbScore1HPrev2": 45,
        "mode": "confirmed"
      },
      "_received": "2026-07-05T01:00:09.784Z",
      "_sample": false,
      "funding": {
        "fundingRate": 0.0001,
        "fundingRatePct": "0.0100%",
        "fundingZone": "ELEVATED",
        "fundingSource": "OKX",
        "nextFundingTime": "1783267200000",
        "conflictLong": false,
        "conflictShort": false,
        "confluenceLong": false,
        "confluenceShort": false,
        "_fetched": "2026-07-05T01:00:09.973Z"
      }
    },
    "4H": {
      "symbol": "ADAUSDT",
      "timeframe": "4H",
      "open": 0.1454,
      "high": 0.1456,
      "low": 0.1434,
      "close": 0.1452,
      "volume": 8371781.3,
      "wickRange": 0.0022,
      "vwap": 0.145,
      "ema50": 0.1521,
      "ema100": null,
      "ema200": 0.1797,
      "sma50": null,
      "sma200": null,
      "rsi": 43.1283,
      "stochK": 56.9092,
      "stochD": 64.7885,
      "macdLine": -0.0016,
      "macdHist": 0.0004,
      "atr": 0.0035,
      "volSMA20": 22888248.535,
      "bbWidth": null,
      "trendBias": -0.5,
      "mfi": 57.05,
      "fracResistance": null,
      "fracSupport": null,
      "fracResActive": 0,
      "fracSupActive": 0,
      "fvgBullActive": 0,
      "fvgBullLo": 0.1445,
      "fvgBullHi": 0.147,
      "fvgBearActive": 0,
      "fvgBearLo": 0.1461,
      "fvgBearHi": 0.1467,
      "coffinFormed": 0,
      "coffinHi": null,
      "coffinLo": null,
      "coffinArmed": 0,
      "coffinBreakLong": 0,
      "coffinBreakShort": 0,
      "coffinAtLevel": 0,
      "ewCount": 0,
      "ewDirection": 1,
      "ewWaveType": "UNKNOWN",
      "ewCorrPattern": "NONE",
      "ewInvalidated": 0,
      "ewBWave": 0,
      "ewDivergence": 0,
      "ewAlternation": "NONE",
      "ewFibTarget": null,
      "ewFibRetrace": null,
      "ewPriorW4High": null,
      "ewPriorW4Low": null,
      "dailyHigh": null,
      "dailyLow": null,
      "dailyOpenHour": null,
      "dailyOpenSession": null,
      "emaStackAligned": 1,
      "volRegime": "NEUTRAL",
      "choch": 0,
      "chochLevel": null,
      "rsiDivBearish": 0,
      "rsiDivBullish": 0,
      "macdDivBearish": 1,
      "macdDivBullish": 1,
      "bosVolConfirmed": 0,
      "bosVolRatio": 0.37,
      "candleType": "PIN_BULL",
      "consolidationForming": 0,
      "consolidationBars": 3,
      "obActive": 0,
      "obType": "NONE",
      "obHigh": null,
      "obLow": null,
      "marketState": null,
      "bdkb": {
        "score": -47,
        "longScore": 0,
        "shortScore": 47,
        "state": "SHORT_BIAS",
        "direction": "SHORT",
        "components": {
          "structure": -0.1,
          "ema": -1,
          "cvd": -1,
          "funding": 0.5,
          "oi": 0
        },
        "cvdSource": "obv_proxy",
        "pppActive": 0,
        "pppSource": "derived",
        "stopLevel": 0.19,
        "tradeReady4H": 0,
        "mode": "confirmed"
      },
      "_received": "2026-06-28T08:00:25.518Z",
      "_sample": false
    }
  },
  "XRPUSDT": {
    "1H": {
      "symbol": "XRPUSDT",
      "timeframe": "1H",
      "open": 1.1623,
      "high": 1.1625,
      "low": 1.1541,
      "close": 1.1574,
      "volume": 3249331.9,
      "wickRange": 0.0084,
      "vwap": 1.1562,
      "ema50": 1.1336,
      "ema100": null,
      "ema200": 1.0935,
      "sma50": 1.1301,
      "sma200": 1.0733,
      "rsi": 55.0965,
      "stochK": 5.2739,
      "stochD": 10.2704,
      "macdLine": 0.0105,
      "macdHist": -0.0018,
      "atr": 0.0106,
      "volSMA20": 4036694.995,
      "bbWidth": 5.0625,
      "trendBias": 0.5,
      "mfi": 66.55,
      "fracResistance": 1.1843,
      "fracSupport": 1.1597,
      "fracResActive": 1,
      "fracSupActive": 0,
      "fvgBullActive": 0,
      "fvgBullLo": 1.1613,
      "fvgBullHi": 1.1672,
      "fvgBearActive": 0,
      "fvgBearLo": 1.1698,
      "fvgBearHi": 1.1736,
      "coffinFormed": 0,
      "coffinHi": null,
      "coffinLo": null,
      "coffinArmed": 0,
      "coffinBreakLong": 0,
      "coffinBreakShort": 0,
      "coffinAtLevel": 0,
      "ewCount": 0,
      "ewDirection": 1,
      "ewWaveType": "UNKNOWN",
      "ewCorrPattern": "NONE",
      "ewInvalidated": 0,
      "ewBWave": 0,
      "ewDivergence": 0,
      "ewAlternation": "NONE",
      "ewFibTarget": null,
      "ewFibRetrace": null,
      "ewPriorW4High": null,
      "ewPriorW4Low": null,
      "dailyHigh": null,
      "dailyLow": null,
      "dailyOpenHour": null,
      "dailyOpenSession": null,
      "emaStackAligned": 1,
      "volRegime": "NEUTRAL",
      "choch": 1,
      "chochLevel": 1.1616,
      "rsiDivBearish": 0,
      "rsiDivBullish": 0,
      "macdDivBearish": 0,
      "macdDivBullish": 0,
      "bosVolConfirmed": 0,
      "bosVolRatio": 0.8,
      "candleType": "NEUTRAL",
      "consolidationForming": 0,
      "consolidationBars": 0,
      "obActive": 0,
      "obType": null,
      "obHigh": null,
      "obLow": null,
      "marketState": null,
      "bdkb": {
        "score": 43,
        "longScore": 43,
        "shortScore": 0,
        "state": "LONG_BIAS",
        "direction": "LONG",
        "components": {
          "structure": 1,
          "ema": 1,
          "cvd": 0,
          "funding": -0.5,
          "oi": 0,
          "delta": -0.5
        },
        "cvdSource": "obv_proxy",
        "liquidityEvent": 0,
        "liquidityType": "none",
        "setupReady1H": 0,
        "confirmed1H": 0,
        "pppSource": "derived",
        "stopLevel": 1.0789,
        "tradeReady1H": 0,
        "bdkbScore1HPrev1": 43,
        "bdkbScore1HPrev2": 60,
        "mode": "confirmed"
      },
      "_received": "2026-07-05T00:00:06.371Z",
      "_sample": false,
      "funding": {
        "fundingRate": 0.0000216008938742,
        "fundingRatePct": "0.0022%",
        "fundingZone": "ELEVATED",
        "fundingSource": "OKX",
        "nextFundingTime": "1783267200000",
        "conflictLong": false,
        "conflictShort": false,
        "confluenceLong": false,
        "confluenceShort": false,
        "_fetched": "2026-07-05T00:00:06.527Z"
      }
    },
    "30M": {
      "symbol": "XRPUSDT",
      "timeframe": "30M",
      "open": 1.1521,
      "high": 1.1527,
      "low": 1.147,
      "close": 1.1495,
      "volume": 2152183.2,
      "wickRange": 0.0057,
      "vwap": 1.1514,
      "ema50": 1.1516,
      "ema100": null,
      "ema200": 1.1098,
      "sma50": null,
      "sma200": null,
      "rsi": 39.0476,
      "stochK": 0,
      "stochD": 0.2332,
      "macdLine": 0.0003,
      "macdHist": -0.0033,
      "atr": 0.0067,
      "volSMA20": 1925378.91,
      "bbWidth": 2.8229,
      "trendBias": -0.5,
      "mfi": null,
      "fracResistance": null,
      "fracSupport": null,
      "fracResActive": 0,
      "fracSupActive": 0,
      "fvgBullActive": 0,
      "fvgBullLo": null,
      "fvgBullHi": null,
      "fvgBearActive": 0,
      "fvgBearLo": null,
      "fvgBearHi": null,
      "coffinFormed": 0,
      "coffinHi": null,
      "coffinLo": null,
      "coffinArmed": 0,
      "coffinBreakLong": 0,
      "coffinBreakShort": 0,
      "coffinAtLevel": 0,
      "ewCount": 0,
      "ewDirection": 1,
      "ewWaveType": "UNKNOWN",
      "ewCorrPattern": "NONE",
      "ewInvalidated": 0,
      "ewBWave": 0,
      "ewDivergence": 0,
      "ewAlternation": "NONE",
      "ewFibTarget": null,
      "ewFibRetrace": null,
      "ewPriorW4High": null,
      "ewPriorW4Low": null,
      "dailyHigh": null,
      "dailyLow": null,
      "dailyOpenHour": null,
      "dailyOpenSession": null,
      "emaStackAligned": 0,
      "volRegime": "NEUTRAL",
      "choch": 0,
      "chochLevel": null,
      "rsiDivBearish": 0,
      "rsiDivBullish": 0,
      "macdDivBearish": 0,
      "macdDivBullish": 0,
      "bosVolConfirmed": 0,
      "bosVolRatio": null,
      "candleType": null,
      "consolidationForming": 0,
      "consolidationBars": 0,
      "obActive": 0,
      "obType": null,
      "obHigh": null,
      "obLow": null,
      "marketState": null,
      "bdkb": {
        "score": -41,
        "longScore": 0,
        "shortScore": 41,
        "state": "SHORT_BIAS",
        "direction": "SHORT",
        "components": {
          "structure": -0.25,
          "ema": -0.13,
          "cvd": -1,
          "funding": 0.5,
          "oi": 0,
          "delta": -0.5
        },
        "cvdSource": "obv_proxy",
        "liquidityEvent": 0,
        "liquidityType": "none",
        "setupReady30M": 0,
        "confirmed30M": 0,
        "stopLevel": 1.1843,
        "tradeReady30M": 0,
        "mode": "confirmed"
      },
      "_received": "2026-07-05T01:00:05.744Z",
      "_sample": false,
      "funding": {
        "fundingRate": 0.0000454552965586,
        "fundingRatePct": "0.0045%",
        "fundingZone": "ELEVATED",
        "fundingSource": "OKX",
        "nextFundingTime": "1783267200000",
        "conflictLong": false,
        "conflictShort": false,
        "confluenceLong": false,
        "confluenceShort": false,
        "_fetched": "2026-07-05T01:00:05.899Z"
      }
    },
    "15M": {
      "symbol": "XRPUSDT",
      "timeframe": "15M",
      "open": 1.148,
      "high": 1.1482,
      "low": 1.1431,
      "close": 1.1464,
      "volume": 1050392.3,
      "wickRange": 0.0051,
      "vwap": 1.1502,
      "ema50": 1.1589,
      "ema100": null,
      "ema200": 1.1341,
      "sma50": null,
      "sma200": null,
      "rsi": 26.1047,
      "stochK": 0,
      "stochD": 0,
      "macdLine": -0.0047,
      "macdHist": -0.0015,
      "atr": 0.0044,
      "volSMA20": 695531.915,
      "bbWidth": 2.1776,
      "trendBias": -0.5,
      "mfi": 5.6,
      "fracResistance": 1.1602,
      "fracSupport": 1.1541,
      "fracResActive": 1,
      "fracSupActive": 0,
      "fvgBullActive": 0,
      "fvgBullLo": 1.165,
      "fvgBullHi": 1.1658,
      "fvgBearActive": 0,
      "fvgBearLo": 1.1527,
      "fvgBearHi": 1.1537,
      "coffinFormed": 0,
      "coffinHi": 1.1537,
      "coffinLo": 1.1517,
      "coffinArmed": 0,
      "coffinBreakLong": 0,
      "coffinBreakShort": 0,
      "coffinAtLevel": 0,
      "ewCount": 0,
      "ewDirection": 1,
      "ewWaveType": "UNKNOWN",
      "ewCorrPattern": "NONE",
      "ewInvalidated": 0,
      "ewBWave": 0,
      "ewDivergence": 0,
      "ewAlternation": "NONE",
      "ewFibTarget": null,
      "ewFibRetrace": null,
      "ewPriorW4High": null,
      "ewPriorW4Low": null,
      "dailyHigh": null,
      "dailyLow": null,
      "dailyOpenHour": null,
      "dailyOpenSession": null,
      "emaStackAligned": 0,
      "volRegime": "COMPRESSION",
      "choch": 0,
      "chochLevel": null,
      "rsiDivBearish": 0,
      "rsiDivBullish": 0,
      "macdDivBearish": 0,
      "macdDivBullish": 0,
      "bosVolConfirmed": 0,
      "bosVolRatio": null,
      "candleType": null,
      "consolidationForming": 0,
      "consolidationBars": 0,
      "obActive": 0,
      "obType": null,
      "obHigh": null,
      "obLow": null,
      "marketState": null,
      "bdkb": {
        "score": -56,
        "longScore": 0,
        "shortScore": 56,
        "state": "SHORT_BIAS",
        "direction": "SHORT",
        "components": {
          "structure": -1,
          "ema": -0.25,
          "cvd": -1,
          "funding": 1,
          "oi": 0,
          "delta": -0.5
        },
        "cvdSource": "obv_proxy",
        "liquidityEvent": 1,
        "liquidityType": "wick_reclaim",
        "setupReady15M": 1,
        "confirmed15M": 0,
        "stopLevel": 1.1843,
        "tradeReady15M": 0,
        "mode": "confirmed"
      },
      "_received": "2026-07-05T01:30:04.740Z",
      "_sample": false
    },
    "4H": {
      "symbol": "XRPUSDT",
      "timeframe": "4H",
      "open": 1.138,
      "high": 1.1496,
      "low": 1.1332,
      "close": 1.1396,
      "volume": 13428380.2,
      "wickRange": 0.0164,
      "vwap": 1.1394,
      "ema50": 1.0834,
      "ema100": null,
      "ema200": 1.1453,
      "sma50": null,
      "sma200": null,
      "rsi": 73.9441,
      "stochK": 100,
      "stochD": 100,
      "macdLine": 0.0211,
      "macdHist": 0.0064,
      "atr": 0.0183,
      "volSMA20": 14269446.445,
      "bbWidth": null,
      "trendBias": 0.5,
      "mfi": 87.97,
      "fracResistance": null,
      "fracSupport": null,
      "fracResActive": 0,
      "fracSupActive": 0,
      "fvgBullActive": 0,
      "fvgBullLo": 1.1238,
      "fvgBullHi": 1.1274,
      "fvgBearActive": 0,
      "fvgBearLo": 1.0514,
      "fvgBearHi": 1.0556,
      "coffinFormed": 0,
      "coffinHi": null,
      "coffinLo": null,
      "coffinArmed": 0,
      "coffinBreakLong": 0,
      "coffinBreakShort": 0,
      "coffinAtLevel": 0,
      "ewCount": 0,
      "ewDirection": 1,
      "ewWaveType": "UNKNOWN",
      "ewCorrPattern": "NONE",
      "ewInvalidated": 0,
      "ewBWave": 0,
      "ewDivergence": 0,
      "ewAlternation": "NONE",
      "ewFibTarget": null,
      "ewFibRetrace": null,
      "ewPriorW4High": null,
      "ewPriorW4Low": null,
      "dailyHigh": null,
      "dailyLow": null,
      "dailyOpenHour": null,
      "dailyOpenSession": null,
      "emaStackAligned": 0,
      "volRegime": "NEUTRAL",
      "choch": 0,
      "chochLevel": null,
      "rsiDivBearish": 0,
      "rsiDivBullish": 0,
      "macdDivBearish": 0,
      "macdDivBullish": 0,
      "bosVolConfirmed": 0,
      "bosVolRatio": 0.94,
      "candleType": "PIN_BEAR",
      "consolidationForming": 0,
      "consolidationBars": 3,
      "obActive": 0,
      "obType": "NONE",
      "obHigh": null,
      "obLow": null,
      "marketState": null,
      "bdkb": {
        "score": 41,
        "longScore": 41,
        "shortScore": 0,
        "state": "LONG_BIAS",
        "direction": "LONG",
        "components": {
          "structure": 0.5,
          "ema": 0.25,
          "cvd": 1,
          "funding": -1,
          "oi": 0
        },
        "cvdSource": "obv_proxy",
        "pppActive": 0,
        "pppSource": "derived",
        "stopLevel": 1.022,
        "tradeReady4H": 0,
        "mode": "confirmed"
      },
      "_received": "2026-07-04T08:00:04.792Z",
      "_sample": false
    }
  }
}