{
  "symbol": "ADAUSDT",
  "timeframe": "30M",
  "open": 0.2618,
  "high": 0.2618,
  "low": 0.261,
  "close": 0.2612,
  "volume": 368824.5,
  "wickRange": 0.0008,
  "vwap": 0.2616,
  "ema50": 0.2634,
  "ema100": null,
  "ema200": 0.2678,
  "sma50": null,
  "sma200": null,
  "rsi": 44.8506,
  "stochK": 76.8554,
  "stochD": 76.0142,
  "macdLine": -0.0005,
  "macdHist": 0.0002,
  "atr": 0.0011,
  "volSMA20": 1005504.695,
  "bbWidth": 0.6457,
  "trendBias": 0,
  "ewCount": 0,
  "ewDirection": 1,
  "ewWaveType": "UNKNOWN",
  "ewCorrPattern": "NONE",
  "ewInvalidated": 0,
  "ewBWave": 0,
  "ewDivergence": 0,
  "ewAlternation": "NONE",
  "ewFibTarget": null,
  "ewFibRetrace": null,
  "ewPriorW4High": null,
  "ewPriorW4Low": null,
  "dailyHigh": null,
  "dailyLow": null,
  "dailyOpenHour": null,
  "dailyOpenSession": null,
  "bdkb": {
    "score": -29,
    "longScore": 0,
    "shortScore": 29,
    "state": "NEUTRAL",
    "direction": "NEUTRAL",
    "components": {
      "structure": -0.25,
      "ema": -1,
      "cvd": 0,
      "funding": 0.5,
      "oi": 0,
      "delta": -1
    },
    "cvdSource": "obv_proxy",
    "liquidityEvent": 0,
    "liquidityType": "none",
    "setupReady30M": 0,
    "confirmed30M": 0,
    "stopLevel": null,
    "tradeReady30M": 0,
    "mode": "confirmed"
  },
  "_received": "2026-05-16T04:00:13.339Z",
  "_sample": false,
  "funding": {
    "fundingRate": 0.0000450708864422,
    "fundingRatePct": "0.0045%",
    "fundingZone": "ELEVATED",
    "fundingSource": "OKX",
    "nextFundingTime": "1778947200000",
    "conflictLong": false,
    "conflictShort": false,
    "confluenceLong": false,
    "confluenceShort": false,
    "_fetched": "2026-05-16T04:00:13.494Z"
  }
}