{
  "symbol": "BTCUSDT",
  "timeframe": "15M",
  "open": 78058.02,
  "high": 78188.48,
  "low": 78031,
  "close": 78122.91,
  "volume": 200.8752,
  "wickRange": 157.48,
  "vwap": 78639.8684,
  "ema50": 78862.9619,
  "ema100": null,
  "ema200": 79692.0304,
  "sma50": null,
  "sma200": null,
  "rsi": 27.7747,
  "stochK": 53.6232,
  "stochD": 56.7755,
  "macdLine": -226.2213,
  "macdHist": -38.3102,
  "atr": 169.7159,
  "volSMA20": 167.507,
  "bbWidth": 1.6254,
  "trendBias": 0,
  "ewCount": 0,
  "ewDirection": 1,
  "ewWaveType": "UNKNOWN",
  "ewCorrPattern": "NONE",
  "ewInvalidated": 0,
  "ewBWave": 0,
  "ewDivergence": 0,
  "ewAlternation": "NONE",
  "ewFibTarget": null,
  "ewFibRetrace": null,
  "ewPriorW4High": null,
  "ewPriorW4Low": null,
  "dailyHigh": null,
  "dailyLow": null,
  "dailyOpenHour": null,
  "dailyOpenSession": null,
  "bdkb": {
    "score": -23,
    "longScore": 0,
    "shortScore": 23,
    "state": "NEUTRAL",
    "direction": "NEUTRAL",
    "components": {
      "structure": -1,
      "ema": -1,
      "cvd": 0,
      "funding": 1,
      "oi": 0,
      "delta": 0.5
    },
    "cvdSource": "obv_proxy",
    "liquidityEvent": 0,
    "liquidityType": "none",
    "setupReady15M": 0,
    "confirmed15M": 0,
    "stopLevel": null,
    "tradeReady15M": 0,
    "mode": "confirmed"
  },
  "_received": "2026-05-16T09:45:02.846Z",
  "_sample": false
}