{
  "symbol": "BTCUSDT",
  "timeframe": "15M",
  "open": 63191.03,
  "high": 63216,
  "low": 63123.73,
  "close": 63198.44,
  "volume": 107.9029,
  "wickRange": 92.27,
  "vwap": 62994.5761,
  "ema50": 63176.5503,
  "ema100": null,
  "ema200": 62885.6199,
  "sma50": null,
  "sma200": null,
  "rsi": 51.5494,
  "stochK": 28.4116,
  "stochD": 37.8974,
  "macdLine": 48.7494,
  "macdHist": -0.7782,
  "atr": 199.0464,
  "volSMA20": 224.4418,
  "bbWidth": 1.353,
  "trendBias": 0,
  "mfi": 52.93,
  "fracResistance": 63506,
  "fracSupport": 63012,
  "fracResActive": 1,
  "fracSupActive": 1,
  "fvgBullActive": 0,
  "fvgBullLo": 62911.26,
  "fvgBullHi": 63220.09,
  "fvgBearActive": 0,
  "fvgBearLo": 63207.12,
  "fvgBearHi": 63298.42,
  "coffinFormed": 0,
  "coffinHi": 63355.58,
  "coffinLo": 63298.43,
  "coffinArmed": 0,
  "coffinBreakLong": 0,
  "coffinBreakShort": 0,
  "coffinAtLevel": 1,
  "ewCount": 0,
  "ewDirection": 1,
  "ewWaveType": "UNKNOWN",
  "ewCorrPattern": "NONE",
  "ewInvalidated": 0,
  "ewBWave": 0,
  "ewDivergence": 0,
  "ewAlternation": "NONE",
  "ewFibTarget": null,
  "ewFibRetrace": null,
  "ewPriorW4High": null,
  "ewPriorW4Low": null,
  "dailyHigh": null,
  "dailyLow": null,
  "dailyOpenHour": null,
  "dailyOpenSession": null,
  "emaStackAligned": 0,
  "volRegime": "NEUTRAL",
  "choch": 0,
  "chochLevel": null,
  "rsiDivBearish": 0,
  "rsiDivBullish": 0,
  "macdDivBearish": 0,
  "macdDivBullish": 0,
  "bosVolConfirmed": 0,
  "bosVolRatio": null,
  "candleType": null,
  "consolidationForming": 0,
  "consolidationBars": 0,
  "obActive": 0,
  "obType": null,
  "obHigh": null,
  "obLow": null,
  "marketState": null,
  "bdkb": {
    "score": 37,
    "longScore": 37,
    "shortScore": 0,
    "state": "NEUTRAL",
    "direction": "NEUTRAL",
    "components": {
      "structure": 0.25,
      "ema": 0.13,
      "cvd": 1,
      "funding": 0,
      "oi": 0,
      "delta": 0
    },
    "cvdSource": "obv_proxy",
    "liquidityEvent": 1,
    "liquidityType": "wick_reclaim",
    "setupReady15M": 0,
    "confirmed15M": 0,
    "stopLevel": null,
    "tradeReady15M": 0,
    "mode": "confirmed"
  },
  "_received": "2026-06-09T08:00:11.451Z",
  "_sample": false
}