{
  "symbol": "BTCUSDT",
  "timeframe": "15M",
  "open": 73501.32,
  "high": 73553.72,
  "low": 73501.32,
  "close": 73520.01,
  "volume": 26.6484,
  "wickRange": 52.4,
  "vwap": 73535.0802,
  "ema50": 73559.4262,
  "ema100": null,
  "ema200": 73823.1466,
  "sma50": null,
  "sma200": null,
  "rsi": 48.8567,
  "stochK": 41.3769,
  "stochD": 24.5593,
  "macdLine": -33.8945,
  "macdHist": -15.7159,
  "atr": 133.1948,
  "volSMA20": 99.8065,
  "bbWidth": 0.675,
  "trendBias": 0,
  "mfi": 51.74,
  "fracResistance": 73796.43,
  "fracSupport": 73216,
  "fracResActive": 1,
  "fracSupActive": 1,
  "fvgBullActive": 0,
  "fvgBullLo": 73402.85,
  "fvgBullHi": 73501.32,
  "fvgBearActive": 0,
  "fvgBearLo": 73348,
  "fvgBearHi": 73352.03,
  "coffinFormed": 0,
  "coffinHi": 73538,
  "coffinLo": 73489.99,
  "coffinArmed": 0,
  "coffinBreakLong": 0,
  "coffinBreakShort": 0,
  "coffinAtLevel": 1,
  "ewCount": 0,
  "ewDirection": 1,
  "ewWaveType": "UNKNOWN",
  "ewCorrPattern": "NONE",
  "ewInvalidated": 0,
  "ewBWave": 0,
  "ewDivergence": 0,
  "ewAlternation": "NONE",
  "ewFibTarget": null,
  "ewFibRetrace": null,
  "ewPriorW4High": null,
  "ewPriorW4Low": null,
  "dailyHigh": null,
  "dailyLow": null,
  "dailyOpenHour": null,
  "dailyOpenSession": null,
  "emaStackAligned": 1,
  "volRegime": "COMPRESSION",
  "choch": 0,
  "chochLevel": null,
  "rsiDivBearish": 0,
  "rsiDivBullish": 0,
  "macdDivBearish": 0,
  "macdDivBullish": 0,
  "bosVolConfirmed": 0,
  "bosVolRatio": null,
  "candleType": null,
  "consolidationForming": 0,
  "consolidationBars": 0,
  "obActive": 0,
  "obType": null,
  "obHigh": null,
  "obLow": null,
  "marketState": null,
  "bdkb": {
    "score": -13,
    "longScore": 0,
    "shortScore": 13,
    "state": "NEUTRAL",
    "direction": "NEUTRAL",
    "components": {
      "structure": -0.25,
      "ema": -1,
      "cvd": 0,
      "funding": 0,
      "oi": 0,
      "delta": 0.5
    },
    "cvdSource": "obv_proxy",
    "liquidityEvent": 1,
    "liquidityType": "wick_reclaim",
    "setupReady15M": 0,
    "confirmed15M": 0,
    "stopLevel": null,
    "tradeReady15M": 0,
    "mode": "confirmed"
  },
  "_received": "2026-05-30T05:30:02.594Z",
  "_sample": false
}