{
  "symbol": "ETHUSDT",
  "timeframe": "15M",
  "open": 2282.21,
  "high": 2286.58,
  "low": 2278.99,
  "close": 2285.28,
  "volume": 1223.3331,
  "wickRange": 7.59,
  "vwap": 2281.1386,
  "ema20": 2278.2729,
  "ema50": 2280.965,
  "ema200": 2302.1713,
  "rsi": 57.7623,
  "stochK": 89.5229,
  "stochD": 84.0761,
  "macdLine": 0.7077,
  "macdHist": 1.6609,
  "atr": 7.7151,
  "bbWidth": 0.8629,
  "volSMA20": 2936.4751,
  "trendBias": 0,
  "bdkb": {
    "score": 59,
    "longScore": 59,
    "shortScore": 0,
    "state": "LONG_BIAS",
    "direction": "LONG",
    "components": {
      "structure": 1,
      "ema": 0.25,
      "cvd": 1,
      "funding": -0.5,
      "oi": 0,
      "delta": 0.5
    },
    "cvdSource": "obv_proxy",
    "liquidityEvent": 1,
    "liquidityType": "swing_break_reclaim",
    "setupReady15M": 1,
    "confirmed15M": 0,
    "stopLevel": 2258.24,
    "tradeReady15M": 0,
    "mode": "confirmed"
  },
  "sma50": null,
  "sma200": null,
  "_received": "2026-04-28T17:30:09.910Z",
  "_sample": false
}