{
  "symbol": "ETHUSDT",
  "timeframe": "15M",
  "open": 2313.13,
  "high": 2313.13,
  "low": 2307.2,
  "close": 2309.37,
  "volume": 1769.4085,
  "wickRange": 5.93,
  "vwap": 2315.2239,
  "ema20": 2320.6602,
  "ema50": 2327.8915,
  "ema200": 2331.6993,
  "rsi": 34.1909,
  "stochK": 52.36,
  "stochD": 49.1709,
  "macdLine": -6.7922,
  "macdHist": -1.0687,
  "atr": 6.5867,
  "bbWidth": 2.0278,
  "volSMA20": 2526.2705,
  "trendBias": 0,
  "bdkb": {
    "score": -59,
    "longScore": 0,
    "shortScore": 59,
    "state": "SHORT_BIAS",
    "direction": "SHORT",
    "components": {
      "structure": -0.25,
      "ema": -1,
      "cvd": -1,
      "funding": 0.5,
      "oi": 0,
      "delta": -0.75
    },
    "cvdSource": "obv_proxy",
    "liquidityEvent": 0,
    "liquidityType": "none",
    "setupReady15M": 0,
    "confirmed15M": 0,
    "stopLevel": 2345.68,
    "tradeReady15M": 0,
    "mode": "confirmed"
  },
  "sma50": null,
  "sma200": null,
  "_received": "2026-05-12T04:00:12.782Z",
  "_sample": false
}