{
  "symbol": "SOLUSDT",
  "timeframe": "4H",
  "open": 82.08,
  "high": 83.74,
  "low": 81.68,
  "close": 81.94,
  "volume": 392865.79,
  "wickRange": 2.06,
  "vwap": 81.3149,
  "ema50": 78.7549,
  "ema100": null,
  "ema200": 75.3623,
  "sma50": null,
  "sma200": null,
  "rsi": 59.5391,
  "stochK": 57.1526,
  "stochD": 35.5907,
  "macdLine": 0.7247,
  "macdHist": -0.1987,
  "atr": 1.4632,
  "volSMA20": 312212.9681,
  "bbWidth": null,
  "trendBias": 0,
  "mfi": 57.68,
  "fracResistance": null,
  "fracSupport": null,
  "fracResActive": 0,
  "fracSupActive": 0,
  "fvgBullActive": 0,
  "fvgBullLo": 81.54,
  "fvgBullHi": 81.68,
  "fvgBearActive": 0,
  "fvgBearLo": 80.87,
  "fvgBearHi": 81.45,
  "coffinFormed": 0,
  "coffinHi": null,
  "coffinLo": null,
  "coffinArmed": 0,
  "coffinBreakLong": 0,
  "coffinBreakShort": 0,
  "coffinAtLevel": 0,
  "ewCount": 0,
  "ewDirection": 1,
  "ewWaveType": "UNKNOWN",
  "ewCorrPattern": "NONE",
  "ewInvalidated": 0,
  "ewBWave": 0,
  "ewDivergence": 0,
  "ewAlternation": "NONE",
  "ewFibTarget": null,
  "ewFibRetrace": null,
  "ewPriorW4High": null,
  "ewPriorW4Low": null,
  "dailyHigh": null,
  "dailyLow": null,
  "dailyOpenHour": null,
  "dailyOpenSession": null,
  "emaStackAligned": 1,
  "volRegime": "NEUTRAL",
  "choch": 0,
  "chochLevel": null,
  "rsiDivBearish": 0,
  "rsiDivBullish": 0,
  "macdDivBearish": 1,
  "macdDivBullish": 0,
  "bosVolConfirmed": 0,
  "bosVolRatio": 1.26,
  "candleType": "PIN_BEAR",
  "consolidationForming": 0,
  "consolidationBars": 0,
  "obActive": 0,
  "obType": "NONE",
  "obHigh": null,
  "obLow": null,
  "marketState": null,
  "bdkb": {
    "score": 17,
    "longScore": 17,
    "shortScore": 0,
    "state": "NEUTRAL",
    "direction": "NEUTRAL",
    "components": {
      "structure": 0.1,
      "ema": 1,
      "cvd": 0,
      "funding": -0.5,
      "oi": -1
    },
    "cvdSource": "obv_proxy",
    "pppActive": 1,
    "pppSource": "derived",
    "stopLevel": null,
    "tradeReady4H": 0,
    "mode": "confirmed"
  },
  "_received": "2026-07-07T00:00:14.415Z",
  "_sample": false
}