{
  "symbol": "XRPUSDT",
  "timeframe": "30M",
  "open": 1.3803,
  "high": 1.3821,
  "low": 1.3795,
  "close": 1.3803,
  "volume": 660551,
  "wickRange": 0.0026,
  "vwap": 1.3783,
  "ema50": 1.374,
  "ema100": null,
  "ema200": 1.3847,
  "sma50": null,
  "sma200": null,
  "rsi": 56.0807,
  "stochK": 59.4493,
  "stochD": 49.7837,
  "macdLine": 0.0018,
  "macdHist": 0,
  "atr": 0.0051,
  "volSMA20": 1380857.695,
  "bbWidth": 1.4185,
  "trendBias": 0,
  "mfi": null,
  "fracResistance": null,
  "fracSupport": null,
  "fracResActive": 0,
  "fracSupActive": 0,
  "fvgBullActive": 0,
  "fvgBullLo": null,
  "fvgBullHi": null,
  "fvgBearActive": 0,
  "fvgBearLo": null,
  "fvgBearHi": null,
  "coffinFormed": 0,
  "coffinHi": null,
  "coffinLo": null,
  "coffinArmed": 0,
  "coffinBreakLong": 0,
  "coffinBreakShort": 0,
  "coffinAtLevel": 0,
  "ewCount": 0,
  "ewDirection": 1,
  "ewWaveType": "UNKNOWN",
  "ewCorrPattern": "NONE",
  "ewInvalidated": 0,
  "ewBWave": 0,
  "ewDivergence": 0,
  "ewAlternation": "NONE",
  "ewFibTarget": null,
  "ewFibRetrace": null,
  "ewPriorW4High": null,
  "ewPriorW4Low": null,
  "dailyHigh": null,
  "dailyLow": null,
  "dailyOpenHour": null,
  "dailyOpenSession": null,
  "bdkb": {
    "score": 11,
    "longScore": 11,
    "shortScore": 0,
    "state": "NEUTRAL",
    "direction": "NEUTRAL",
    "components": {
      "structure": 0.25,
      "ema": 0.5,
      "cvd": 0,
      "funding": -0.5,
      "oi": 0,
      "delta": 0
    },
    "cvdSource": "obv_proxy",
    "liquidityEvent": 1,
    "liquidityType": "wick_reclaim",
    "setupReady30M": 0,
    "confirmed30M": 0,
    "stopLevel": null,
    "tradeReady30M": 0,
    "mode": "confirmed"
  },
  "_received": "2026-05-21T09:30:07.240Z",
  "_sample": false,
  "funding": {
    "fundingRate": 0.0001,
    "fundingRatePct": "0.0100%",
    "fundingZone": "ELEVATED",
    "fundingSource": "OKX",
    "nextFundingTime": "1779408000000",
    "conflictLong": false,
    "conflictShort": false,
    "confluenceLong": false,
    "confluenceShort": false,
    "_fetched": "2026-05-21T09:30:07.397Z"
  }
}