{
  "symbol": "XRPUSDT",
  "timeframe": "15M",
  "open": 1.4333,
  "high": 1.4347,
  "low": 1.4327,
  "close": 1.4341,
  "volume": 275846.4,
  "wickRange": 0.002,
  "vwap": 1.4586,
  "ema50": 1.4437,
  "ema100": null,
  "ema200": 1.4552,
  "sma50": null,
  "sma200": null,
  "rsi": 42.2614,
  "stochK": 94.8306,
  "stochD": 84.6375,
  "macdLine": -0.003,
  "macdHist": 0.0005,
  "atr": 0.0036,
  "volSMA20": 512425.215,
  "bbWidth": 0.7504,
  "trendBias": 0,
  "ewCount": 0,
  "ewDirection": 1,
  "ewWaveType": "UNKNOWN",
  "ewCorrPattern": "NONE",
  "ewInvalidated": 0,
  "ewBWave": 0,
  "ewDivergence": 0,
  "ewAlternation": "NONE",
  "ewFibTarget": null,
  "ewFibRetrace": null,
  "ewPriorW4High": null,
  "ewPriorW4Low": null,
  "dailyHigh": null,
  "dailyLow": null,
  "dailyOpenHour": null,
  "dailyOpenSession": null,
  "bdkb": {
    "score": 20,
    "longScore": 20,
    "shortScore": 0,
    "state": "NEUTRAL",
    "direction": "NEUTRAL",
    "components": {
      "structure": -0.25,
      "ema": -1,
      "cvd": 1,
      "funding": 0.5,
      "oi": 0,
      "delta": 0.5
    },
    "cvdSource": "obv_proxy",
    "liquidityEvent": 0,
    "liquidityType": "none",
    "setupReady15M": 0,
    "confirmed15M": 0,
    "stopLevel": null,
    "tradeReady15M": 0,
    "mode": "confirmed"
  },
  "_received": "2026-05-15T23:30:01.550Z",
  "_sample": false
}