{
  "symbol": "XRPUSDT",
  "timeframe": "15M",
  "open": 1.4417,
  "high": 1.4429,
  "low": 1.4399,
  "close": 1.4411,
  "volume": 925230.5,
  "wickRange": 0.003,
  "vwap": 1.4499,
  "ema20": 1.4362,
  "ema50": 1.4423,
  "ema200": 1.4508,
  "rsi": 56.2024,
  "stochK": 94.6896,
  "stochD": 95.5515,
  "macdLine": -0.0003,
  "macdHist": 0.0022,
  "atr": 0.0047,
  "bbWidth": 1.7115,
  "volSMA20": 1138118.02,
  "trendBias": 0,
  "bdkb": {
    "score": 6,
    "longScore": 6,
    "shortScore": 0,
    "state": "NEUTRAL",
    "direction": "NEUTRAL",
    "components": {
      "structure": 0.25,
      "ema": 0.25,
      "cvd": 0,
      "funding": -0.5,
      "oi": 0,
      "delta": 0
    },
    "cvdSource": "obv_proxy",
    "liquidityEvent": 0,
    "liquidityType": "none",
    "setupReady15M": 0,
    "confirmed15M": 0,
    "stopLevel": null,
    "tradeReady15M": 0,
    "mode": "confirmed"
  },
  "sma50": null,
  "sma200": null,
  "_received": "2026-05-12T20:00:09.838Z",
  "_sample": false
}