{
  "symbol": null,
  "timeframe": null,
  "open": 0.2543,
  "high": 0.2553,
  "low": 0.2542,
  "close": 0.2548,
  "volume": 1167697.2,
  "wickRange": 0.0011,
  "vwap": 0.2543,
  "ema20": 0.253,
  "ema50": 0.2525,
  "ema200": 0.2514,
  "rsi": 64.5265,
  "stochK": 86.9085,
  "stochD": 91.4674,
  "macdLine": 0.0005,
  "macdHist": 0.0003,
  "atr": 0.0011,
  "bbWidth": 1.6745,
  "volSMA20": 881926.41,
  "trendBias": 0,
  "bdkb": {
    "score": 40,
    "longScore": 40,
    "shortScore": 0,
    "state": "LONG_BIAS",
    "direction": "LONG",
    "components": {
      "structure": 1,
      "ema": 1,
      "cvd": 0,
      "funding": -0.5,
      "oi": 0,
      "delta": 0.5
    },
    "cvdSource": "obv_proxy",
    "liquidityEvent": 0,
    "liquidityType": "none",
    "setupReady15M": 0,
    "confirmed15M": 0,
    "stopLevel": 0.2507,
    "tradeReady15M": 0,
    "mode": "confirmed"
  },
  "sma50": null,
  "sma200": null,
  "_received": "2026-04-27T01:45:07.342Z",
  "_sample": false
}