{
  "symbol": null,
  "timeframe": null,
  "open": 89.95,
  "high": 90.59,
  "low": 89.89,
  "close": 90.42,
  "volume": 159369.245,
  "vwap": 89.1869,
  "ema20": 88.6669,
  "ema50": 87.2738,
  "ema200": 84.8746,
  "rsi": 66.8073,
  "macdLine": 0.8455,
  "macdHist": 0.1114,
  "atr": 0.9542,
  "bbWidth": 3.8836,
  "volSMA20": 200208.8609,
  "trendBias": 0,
  "bdkb": {
    "score": 70,
    "longScore": 70,
    "shortScore": 15,
    "state": "SETUP",
    "direction": "LONG",
    "components": {
      "structure": 1,
      "ema": 1,
      "vwap": 1,
      "volume": 0,
      "rsi": 1,
      "liquidity": 0
    },
    "liquidityEvent": 1,
    "liquidityType": "swing_break_reclaim",
    "setupReady1H": 1,
    "confirmed1H": 0,
    "ppp": null,
    "stopLevel": 83.8,
    "tradeReady1H": 0,
    "mode": "confirmed"
  },
  "sma50": null,
  "sma200": null,
  "stochK": null,
  "stochD": null,
  "_received": "2026-04-17T17:00:07.501Z",
  "_sample": false
}